Workbook
Name Slicer_RegionID: #N/A
Name Slicer_Units: #N/A

Sheet 00_ReadMe
A1: Project
B3: MadeUP FP&A Model
A5: Reporting Date
B7: 46203
A9: Historical Actuals
B11: January 2025 – December 2025
A13: Current-Year Actuals
B15: January 2026 – June 2026
A17: Forecast
B19: July 2026 – December 2026
A21: Data
B23: Synthetic
A25: Purpose
B27: Demonstrate an end-to-end FP&A workflow.

Sheet 01_Assumptions
A1: Revenue Assumptions
A3: Business Unit | B3: Volume Growth | C3: Price Growth
A4: Devices | B4: 0.06 | C4: 0.02
A5: Cloud & Software | B5: 0.1 | C5: 0.03
A6: Digital Services | B6: 0.08 | C6: 0.02
A8: Opex Assumptions
A10: Department | B10: Budget Growth
A11: Sales | B11: 0.06
A12: Marketing | B12: 0.07
A13: R&D | B13: 0.09
A14: G&A | B14: 0.05
A15: IT | B15: 0.08
A16: Customer Operations | B16: 0.06
A17: HR | B17: 0.05
A18: Facilities | B18: 0.05
A20: Headcount Assumptions
A22: Department | B22: Headcount Growth
A23: Sales | B23: 0.05
A24: Marketing | B24: 0.06
A25: R&D | B25: 0.08
A26: G&A | B26: 0.03
A27: IT | B27: 0.07
A28: Customer Operations | B28: 0.05
A29: HR | B29: 0.04
A30: Facilities | B30: 0.02
A32: Revenue Growth Assumptions
A34: Scenario | B34: Revenue Growth Adjustment
A35: Downside | B35: -3 percentage points
A36: Base | B36: 0
A37: Upside | B37: +3 percentage points

Sheet 02_Actual_Revenue
A1: MonthStart | B1: ProductID | C1: RegionID | D1: Units | E1: ASP | F1: Revenue | G1: COGS | H1: COGS RATE
A2: 45658 | B2: P001 | C2: R01 | D2: 230000 | E2: 699 | F2: 160770000 | G2: 99677400 | H2: =G2/F2 -> 0.62
A3: 45658 | B3: P001 | C3: R02 | D3: 195500 | E3: 699 | F3: 136654500 | G3: 84725790 | H3: =G3/F3 -> 0.62
A4: 45658 | B4: P001 | C4: R03 | D4: 218500 | E4: 699 | F4: 152731500 | G4: 94693530 | H4: =G4/F4 -> 0.62
A5: 45658 | B5: P001 | C5: R04 | D5: 126500 | E5: 699 | F5: 88423500 | G5: 54822570 | H5: =G5/F5 -> 0.62
A6: 45658 | B6: P002 | C6: R01 | D6: 110400 | E6: 999 | F6: 110289600 | G6: 63967968 | H6: =G6/F6 -> 0.58
A7: 45658 | B7: P002 | C7: R02 | D7: 93840 | E7: 999 | F7: 93746160 | G7: 54372773 | H7: =G7/F7 -> 0.58
A8: 45658 | B8: P002 | C8: R03 | D8: 104880 | E8: 999 | F8: 104775120 | G8: 60769570 | H8: =G8/F8 -> 0.58
A9: 45658 | B9: P002 | C9: R04 | D9: 60720 | E9: 999 | F9: 60659280 | G9: 35182382 | H9: =G9/F9 -> 0.58
A10: 45658 | B10: P003 | C10: R01 | D10: 128800 | E10: 549 | F10: 70711200 | G10: 42426720 | H10: =G10/F10 -> 0.6
A11: 45658 | B11: P003 | C11: R02 | D11: 109480 | E11: 549 | F11: 60104520 | G11: 36062712 | H11: =G11/F11 -> 0.6
A12: 45658 | B12: P003 | C12: R03 | D12: 122360 | E12: 549 | F12: 67175640 | G12: 40305384 | H12: =G12/F12 -> 0.6
A13: 45658 | B13: P003 | C13: R04 | D13: 70840 | E13: 549 | F13: 38891160 | G13: 23334696 | H13: =G13/F13 -> 0.6
... A721: 46174 | B721: P010 | C721: R04 | D721: 504900 | E721: 8 | F721: 4039200 | G721: 605880 | H721: =G721/F721 -> 0.15
A723: Total Actual Revenue | B723: =SUM(F2:F721) -> 34530245600
A724: Total Actual COGS | B724: =SUM(G2:G721) -> 1.8854969e+10
A725: Total Actual Gross Profit | B725: =B723-B724 -> 1.5675277e+10
A726: Actual Gross Margin % | B726: =B725/B723 -> 0.45395787

Sheet 03_Actual_Opex
A1: MonthStart | B1: DepartmentID | C1: DepartmentName | D1: ExpenseCategoryID | E1: Amount
A2: 45658 | B2: D01 | C2: Sales | D2: A01 | E2: 8000000
A3: 45658 | B3: D01 | C3: Sales | D3: A02 | E3: 8000000
A4: 45658 | B4: D01 | C4: Sales | D4: A03 | E4: 8000000
A5: 45658 | B5: D01 | C5: Sales | D5: A04 | E5: 8000000
A6: 45658 | B6: D02 | C6: Marketing | D6: A01 | E6: 30000000
A7: 45658 | B7: D02 | C7: Marketing | D7: A02 | E7: 30000000
A8: 45658 | B8: D02 | C8: Marketing | D8: A03 | E8: 30000000
A9: 45658 | B9: D02 | C9: Marketing | D9: A04 | E9: 30000000
A10: 45658 | B10: D03 | C10: R&D | D10: A01 | E10: 20000000
A11: 45658 | B11: D03 | C11: R&D | D11: A02 | E11: 20000000
A12: 45658 | B12: D03 | C12: R&D | D12: A03 | E12: 20000000
A13: 45658 | B13: D03 | C13: R&D | D13: A04 | E13: 20000000
... A577: 46174 | B577: D08 | C577: Facilities | D577: A04 | E577: 8000000
A579: Total Actual Opex | B579: =SUM(E2:E577) -> 7128000000

Sheet 04_Actual_Headcount
A1: MonthStart | B1: DepartmentID | C1: Headcount | D1: AverageMonthlySalary
A2: 45658 | B2: D01 | C2: 700 | D2: 70000
A3: 45658 | B3: D02 | C3: 450 | D3: 75000
A4: 45658 | B4: D03 | C4: 1100 | D4: 95000
A5: 45658 | B5: D04 | C5: 400 | D5: 85000
A6: 45658 | B6: D05 | C6: 350 | D6: 90000
A7: 45658 | B7: D06 | C7: 700 | D7: 65000
A8: 45658 | B8: D07 | C8: 150 | D8: 70000
A9: 45658 | B9: D08 | C9: 200 | D9: 55000
A10: 45689 | B10: D01 | C10: 700 | D10: 70000
A11: 45689 | B11: D02 | C11: 450 | D11: 75000
A12: 45689 | B12: D03 | C12: 1100 | D12: 95000
A13: 45689 | B13: D04 | C13: 400 | D13: 85000
... A145: 46174 | B145: D08 | C145: 200 | D145: 55000

Sheet 05_Budget
A1: Month | B1: ProductID | C1: RegionID | D1: BusinessUnit | E1: Budget Units | F1: Budget ASP | G1: Budget Revenue | H1: Budget COGS | I1: Budget Gross Profit | J1: Budget Gross Margin
A2: ='02_Actual_Revenue'!A2 -> 45658 | B2: ='02_Actual_Revenue'!B2 -> P001 | C2: ='02_Actual_Revenue'!C2 -> R01 | D2: ='02_Actual_Revenue'!D2 -> 230000 | E2: =D2*(1+_xlfn.XLOOKUP("Devices",'01_Assumptions'!$A$4:$A$6,'01_Assumptions'!$B$4:$B$6)) -> 243800 | F2: ='02_Actual_Revenue'!E2*(1+_xlfn.XLOOKUP("Devices",'01_Assumptions'!$A$4:$A$6,'01_Assumptions'!$C$4:$C$6)) -> 712.98 | G2: =E2*F2 -> 173824524 | H2: =G2*'02_Actual_Revenue'!H2 -> 1.077712e+08 | I2: =G2-H2 -> 66053319 | J2: =I2/G2 -> 0.38
A3: ='02_Actual_Revenue'!A3 -> 45658 | B3: ='02_Actual_Revenue'!B3 -> P001 | C3: ='02_Actual_Revenue'!C3 -> R02 | D3: ='02_Actual_Revenue'!D3 -> 195500 | E3: =D3*(1+_xlfn.XLOOKUP("Devices",'01_Assumptions'!$A$4:$A$6,'01_Assumptions'!$B$4:$B$6)) -> 207230 | F3: ='02_Actual_Revenue'!E3*(1+_xlfn.XLOOKUP("Devices",'01_Assumptions'!$A$4:$A$6,'01_Assumptions'!$C$4:$C$6)) -> 712.98 | G3: =E3*F3 -> 1.4775085e+08 | H3: =G3*'02_Actual_Revenue'!H3 -> 91605524 | I3: =G3-H3 -> 56145321 | J3: =I3/G3 -> 0.38
A4: ='02_Actual_Revenue'!A4 -> 45658 | B4: ='02_Actual_Revenue'!B4 -> P001 | C4: ='02_Actual_Revenue'!C4 -> R03 | D4: ='02_Actual_Revenue'!D4 -> 218500 | E4: =D4*(1+_xlfn.XLOOKUP("Devices",'01_Assumptions'!$A$4:$A$6,'01_Assumptions'!$B$4:$B$6)) -> 231610 | F4: ='02_Actual_Revenue'!E4*(1+_xlfn.XLOOKUP("Devices",'01_Assumptions'!$A$4:$A$6,'01_Assumptions'!$C$4:$C$6)) -> 712.98 | G4: =E4*F4 -> 1.651333e+08 | H4: =G4*'02_Actual_Revenue'!H4 -> 1.0238264e+08 | I4: =G4-H4 -> 62750653 | J4: =I4/G4 -> 0.38
A5: ='02_Actual_Revenue'!A5 -> 45658 | B5: ='02_Actual_Revenue'!B5 -> P001 | C5: ='02_Actual_Revenue'!C5 -> R04 | D5: ='02_Actual_Revenue'!D5 -> 126500 | E5: =D5*(1+_xlfn.XLOOKUP("Devices",'01_Assumptions'!$A$4:$A$6,'01_Assumptions'!$B$4:$B$6)) -> 134090 | F5: ='02_Actual_Revenue'!E5*(1+_xlfn.XLOOKUP("Devices",'01_Assumptions'!$A$4:$A$6,'01_Assumptions'!$C$4:$C$6)) -> 712.98 | G5: =E5*F5 -> 95603488 | H5: =G5*'02_Actual_Revenue'!H5 -> 59274163 | I5: =G5-H5 -> 36329326 | J5: =I5/G5 -> 0.38
A6: ='02_Actual_Revenue'!A6 -> 45658 | B6: ='02_Actual_Revenue'!B6 -> P002 | C6: ='02_Actual_Revenue'!C6 -> R01 | D6: ='02_Actual_Revenue'!D6 -> 110400 | E6: =D6*(1+_xlfn.XLOOKUP("Devices",'01_Assumptions'!$A$4:$A$6,'01_Assumptions'!$B$4:$B$6)) -> 117024 | F6: ='02_Actual_Revenue'!E6*(1+_xlfn.XLOOKUP("Devices",'01_Assumptions'!$A$4:$A$6,'01_Assumptions'!$C$4:$C$6)) -> 1018.98 | G6: =E6*F6 -> 1.1924512e+08 | H6: =G6*'02_Actual_Revenue'!H6 -> 69162167 | I6: =G6-H6 -> 50082949 | J6: =I6/G6 -> 0.42
A7: ='02_Actual_Revenue'!A7 -> 45658 | B7: ='02_Actual_Revenue'!B7 -> P002 | C7: ='02_Actual_Revenue'!C7 -> R02 | D7: ='02_Actual_Revenue'!D7 -> 93840 | E7: =D7*(1+_xlfn.XLOOKUP("Devices",'01_Assumptions'!$A$4:$A$6,'01_Assumptions'!$B$4:$B$6)) -> 99470.4 | F7: ='02_Actual_Revenue'!E7*(1+_xlfn.XLOOKUP("Devices",'01_Assumptions'!$A$4:$A$6,'01_Assumptions'!$C$4:$C$6)) -> 1018.98 | G7: =E7*F7 -> 1.0135835e+08 | H7: =G7*'02_Actual_Revenue'!H7 -> 58787842 | I7: =G7-H7 -> 42570506 | J7: =I7/G7 -> 0.42
A8: ='02_Actual_Revenue'!A8 -> 45658 | B8: ='02_Actual_Revenue'!B8 -> P002 | C8: ='02_Actual_Revenue'!C8 -> R03 | D8: ='02_Actual_Revenue'!D8 -> 104880 | E8: =D8*(1+_xlfn.XLOOKUP("Devices",'01_Assumptions'!$A$4:$A$6,'01_Assumptions'!$B$4:$B$6)) -> 111172.8 | F8: ='02_Actual_Revenue'!E8*(1+_xlfn.XLOOKUP("Devices",'01_Assumptions'!$A$4:$A$6,'01_Assumptions'!$C$4:$C$6)) -> 1018.98 | G8: =E8*F8 -> 1.1328286e+08 | H8: =G8*'02_Actual_Revenue'!H8 -> 65704059 | I8: =G8-H8 -> 47578801 | J8: =I8/G8 -> 0.42
A9: ='02_Actual_Revenue'!A9 -> 45658 | B9: ='02_Actual_Revenue'!B9 -> P002 | C9: ='02_Actual_Revenue'!C9 -> R04 | D9: ='02_Actual_Revenue'!D9 -> 60720 | E9: =D9*(1+_xlfn.XLOOKUP("Devices",'01_Assumptions'!$A$4:$A$6,'01_Assumptions'!$B$4:$B$6)) -> 64363.2 | F9: ='02_Actual_Revenue'!E9*(1+_xlfn.XLOOKUP("Devices",'01_Assumptions'!$A$4:$A$6,'01_Assumptions'!$C$4:$C$6)) -> 1018.98 | G9: =E9*F9 -> 65584814 | H9: =G9*'02_Actual_Revenue'!H9 -> 38039192 | I9: =G9-H9 -> 27545622 | J9: =I9/G9 -> 0.42
A10: ='02_Actual_Revenue'!A10 -> 45658 | B10: ='02_Actual_Revenue'!B10 -> P003 | C10: ='02_Actual_Revenue'!C10 -> R01 | D10: ='02_Actual_Revenue'!D10 -> 128800 | E10: =D10*(1+_xlfn.XLOOKUP("Devices",'01_Assumptions'!$A$4:$A$6,'01_Assumptions'!$B$4:$B$6)) -> 136528 | F10: ='02_Actual_Revenue'!E10*(1+_xlfn.XLOOKUP("Devices",'01_Assumptions'!$A$4:$A$6,'01_Assumptions'!$C$4:$C$6)) -> 559.98 | G10: =E10*F10 -> 76452949 | H10: =G10*'02_Actual_Revenue'!H10 -> 45871770 | I10: =G10-H10 -> 30581180 | J10: =I10/G10 -> 0.4
A11: ='02_Actual_Revenue'!A11 -> 45658 | B11: ='02_Actual_Revenue'!B11 -> P003 | C11: ='02_Actual_Revenue'!C11 -> R02 | D11: ='02_Actual_Revenue'!D11 -> 109480 | E11: =D11*(1+_xlfn.XLOOKUP("Devices",'01_Assumptions'!$A$4:$A$6,'01_Assumptions'!$B$4:$B$6)) -> 116048.8 | F11: ='02_Actual_Revenue'!E11*(1+_xlfn.XLOOKUP("Devices",'01_Assumptions'!$A$4:$A$6,'01_Assumptions'!$C$4:$C$6)) -> 559.98 | G11: =E11*F11 -> 64985007 | H11: =G11*'02_Actual_Revenue'!H11 -> 38991004 | I11: =G11-H11 -> 25994003 | J11: =I11/G11 -> 0.4
A12: ='02_Actual_Revenue'!A12 -> 45658 | B12: ='02_Actual_Revenue'!B12 -> P003 | C12: ='02_Actual_Revenue'!C12 -> R03 | D12: ='02_Actual_Revenue'!D12 -> 122360 | E12: =D12*(1+_xlfn.XLOOKUP("Devices",'01_Assumptions'!$A$4:$A$6,'01_Assumptions'!$B$4:$B$6)) -> 129701.6 | F12: ='02_Actual_Revenue'!E12*(1+_xlfn.XLOOKUP("Devices",'01_Assumptions'!$A$4:$A$6,'01_Assumptions'!$C$4:$C$6)) -> 559.98 | G12: =E12*F12 -> 72630302 | H12: =G12*'02_Actual_Revenue'!H12 -> 43578181 | I12: =G12-H12 -> 29052121 | J12: =I12/G12 -> 0.4
A13: ='02_Actual_Revenue'!A13 -> 45658 | B13: ='02_Actual_Revenue'!B13 -> P003 | C13: ='02_Actual_Revenue'!C13 -> R04 | D13: ='02_Actual_Revenue'!D13 -> 70840 | E13: =D13*(1+_xlfn.XLOOKUP("Devices",'01_Assumptions'!$A$4:$A$6,'01_Assumptions'!$B$4:$B$6)) -> 75090.4 | F13: ='02_Actual_Revenue'!E13*(1+_xlfn.XLOOKUP("Devices",'01_Assumptions'!$A$4:$A$6,'01_Assumptions'!$C$4:$C$6)) -> 559.98 | G13: =E13*F13 -> 42049122 | H13: =G13*'02_Actual_Revenue'!H13 -> 25229473 | I13: =G13-H13 -> 16819649 | J13: =I13/G13 -> 0.4
... A21: ='02_Actual_Revenue'!A21 -> 45658 | B21: ='02_Actual_Revenue'!B21 -> P005 | C21: ='02_Actual_Revenue'!C21 -> R04 | D21: ='02_Actual_Revenue'!D21 -> 91080 | E21: =D21*(1+_xlfn.XLOOKUP("Devices",'01_Assumptions'!$A$4:$A$6,'01_Assumptions'!$B$4:$B$6)) -> 96544.8 | F21: ='02_Actual_Revenue'!E21*(1+_xlfn.XLOOKUP("Devices",'01_Assumptions'!$A$4:$A$6,'01_Assumptions'!$C$4:$C$6)) -> 304.98 | G21: =E21*F21 -> 29444233 | H21: =G21*'02_Actual_Revenue'!H21 -> 14722117 | I21: =G21-H21 -> 14722117 | J21: =I21/G21 -> 0.5
A22: ='02_Actual_Revenue'!A22 -> 45658 | B22: ='02_Actual_Revenue'!B22 -> P006 | C22: ='02_Actual_Revenue'!C22 -> R01 | D22: ='02_Actual_Revenue'!D22 -> 552000 | E22: =D22*(1+_xlfn.XLOOKUP("Cloud & Software",'01_Assumptions'!$A$4:$A$6,'01_Assumptions'!$B$4:$B$6)) -> 607200 | F22: ='02_Actual_Revenue'!E22*(1+_xlfn.XLOOKUP("Cloud & Software",'01_Assumptions'!$A$4:$A$6,'01_Assumptions'!$C$4:$C$6)) -> 40.17 | G22: =E22*F22 -> 24391224 | H22: =G22*'02_Actual_Revenue'!H22 -> 6097806 | I22: =G22-H22 -> 18293418 | J22: =I22/G22 -> 0.75
A23: ='02_Actual_Revenue'!A23 -> 45658 | B23: ='02_Actual_Revenue'!B23 -> P006 | C23: ='02_Actual_Revenue'!C23 -> R02 | D23: ='02_Actual_Revenue'!D23 -> 469200 | E23: =D23*(1+_xlfn.XLOOKUP("Cloud & Software",'01_Assumptions'!$A$4:$A$6,'01_Assumptions'!$B$4:$B$6)) -> 516120 | F23: ='02_Actual_Revenue'!E23*(1+_xlfn.XLOOKUP("Cloud & Software",'01_Assumptions'!$A$4:$A$6,'01_Assumptions'!$C$4:$C$6)) -> 40.17 | G23: =E23*F23 -> 20732540 | H23: =G23*'02_Actual_Revenue'!H23 -> 5183135.1 | I23: =G23-H23 -> 15549405 | J23: =I23/G23 -> 0.75
A24: ='02_Actual_Revenue'!A24 -> 45658 | B24: ='02_Actual_Revenue'!B24 -> P006 | C24: ='02_Actual_Revenue'!C24 -> R03 | D24: ='02_Actual_Revenue'!D24 -> 524400 | E24: =D24*(1+_xlfn.XLOOKUP("Cloud & Software",'01_Assumptions'!$A$4:$A$6,'01_Assumptions'!$B$4:$B$6)) -> 576840 | F24: ='02_Actual_Revenue'!E24*(1+_xlfn.XLOOKUP("Cloud & Software",'01_Assumptions'!$A$4:$A$6,'01_Assumptions'!$C$4:$C$6)) -> 40.17 | G24: =E24*F24 -> 23171663 | H24: =G24*'02_Actual_Revenue'!H24 -> 5792915.7 | I24: =G24-H24 -> 17378747 | J24: =I24/G24 -> 0.75
A25: ='02_Actual_Revenue'!A25 -> 45658 | B25: ='02_Actual_Revenue'!B25 -> P006 | C25: ='02_Actual_Revenue'!C25 -> R04 | D25: ='02_Actual_Revenue'!D25 -> 303600 | E25: =D25*(1+_xlfn.XLOOKUP("Cloud & Software",'01_Assumptions'!$A$4:$A$6,'01_Assumptions'!$B$4:$B$6)) -> 333960 | F25: ='02_Actual_Revenue'!E25*(1+_xlfn.XLOOKUP("Cloud & Software",'01_Assumptions'!$A$4:$A$6,'01_Assumptions'!$C$4:$C$6)) -> 40.17 | G25: =E25*F25 -> 13415173 | H25: =G25*'02_Actual_Revenue'!H25 -> 3353793.3 | I25: =G25-H25 -> 10061380 | J25: =I25/G25 -> 0.75
A26: ='02_Actual_Revenue'!A26 -> 45658 | B26: ='02_Actual_Revenue'!B26 -> P007 | C26: ='02_Actual_Revenue'!C26 -> R01 | D26: ='02_Actual_Revenue'!D26 -> 368000 | E26: =D26*(1+_xlfn.XLOOKUP("Cloud & Software",'01_Assumptions'!$A$4:$A$6,'01_Assumptions'!$B$4:$B$6)) -> 404800 | F26: ='02_Actual_Revenue'!E26*(1+_xlfn.XLOOKUP("Cloud & Software",'01_Assumptions'!$A$4:$A$6,'01_Assumptions'!$C$4:$C$6)) -> 24.72 | G26: =E26*F26 -> 10006656 | H26: =G26*'02_Actual_Revenue'!H26 -> 2001331.2 | I26: =G26-H26 -> 8005324.8 | J26: =I26/G26 -> 0.8
A27: ='02_Actual_Revenue'!A27 -> 45658 | B27: ='02_Actual_Revenue'!B27 -> P007 | C27: ='02_Actual_Revenue'!C27 -> R02 | D27: ='02_Actual_Revenue'!D27 -> 312800 | E27: =D27*(1+_xlfn.XLOOKUP("Cloud & Software",'01_Assumptions'!$A$4:$A$6,'01_Assumptions'!$B$4:$B$6)) -> 344080 | F27: ='02_Actual_Revenue'!E27*(1+_xlfn.XLOOKUP("Cloud & Software",'01_Assumptions'!$A$4:$A$6,'01_Assumptions'!$C$4:$C$6)) -> 24.72 | G27: =E27*F27 -> 8505657.6 | H27: =G27*'02_Actual_Revenue'!H27 -> 1701131.5 | I27: =G27-H27 -> 6804526.1 | J27: =I27/G27 -> 0.8
A28: ='02_Actual_Revenue'!A28 -> 45658 | B28: ='02_Actual_Revenue'!B28 -> P007 | C28: ='02_Actual_Revenue'!C28 -> R03 | D28: ='02_Actual_Revenue'!D28 -> 349600 | E28: =D28*(1+_xlfn.XLOOKUP("Cloud & Software",'01_Assumptions'!$A$4:$A$6,'01_Assumptions'!$B$4:$B$6)) -> 384560 | F28: ='02_Actual_Revenue'!E28*(1+_xlfn.XLOOKUP("Cloud & Software",'01_Assumptions'!$A$4:$A$6,'01_Assumptions'!$C$4:$C$6)) -> 24.72 | G28: =E28*F28 -> 9506323.2 | H28: =G28*'02_Actual_Revenue'!H28 -> 1901264.6 | I28: =G28-H28 -> 7605058.6 | J28: =I28/G28 -> 0.8
A29: ='02_Actual_Revenue'!A29 -> 45658 | B29: ='02_Actual_Revenue'!B29 -> P007 | C29: ='02_Actual_Revenue'!C29 -> R04 | D29: ='02_Actual_Revenue'!D29 -> 202400 | E29: =D29*(1+_xlfn.XLOOKUP("Cloud & Software",'01_Assumptions'!$A$4:$A$6,'01_Assumptions'!$B$4:$B$6)) -> 222640 | F29: ='02_Actual_Revenue'!E29*(1+_xlfn.XLOOKUP("Cloud & Software",'01_Assumptions'!$A$4:$A$6,'01_Assumptions'!$C$4:$C$6)) -> 24.72 | G29: =E29*F29 -> 5503660.8 | H29: =G29*'02_Actual_Revenue'!H29 -> 1100732.2 | I29: =G29-H29 -> 4402928.6 | J29: =I29/G29 -> 0.8
A30: ='02_Actual_Revenue'!A30 -> 45658 | B30: ='02_Actual_Revenue'!B30 -> P008 | C30: ='02_Actual_Revenue'!C30 -> R01 | D30: ='02_Actual_Revenue'!D30 -> 1104000 | E30: =D30*(1+_xlfn.XLOOKUP("Digital Services",'01_Assumptions'!$A$4:$A$6,'01_Assumptions'!$B$4:$B$6)) -> 1192320 | F30: ='02_Actual_Revenue'!E30*(1+_xlfn.XLOOKUP("Digital Services",'01_Assumptions'!$A$4:$A$6,'01_Assumptions'!$C$4:$C$6)) -> 12.24 | G30: =E30*F30 -> 14593997 | H30: =G30*'02_Actual_Revenue'!H30 -> 4378199 | I30: =G30-H30 -> 10215798 | J30: =I30/G30 -> 0.7
A31: ='02_Actual_Revenue'!A31 -> 45658 | B31: ='02_Actual_Revenue'!B31 -> P008 | C31: ='02_Actual_Revenue'!C31 -> R02 | D31: ='02_Actual_Revenue'!D31 -> 938400 | E31: =D31*(1+_xlfn.XLOOKUP("Digital Services",'01_Assumptions'!$A$4:$A$6,'01_Assumptions'!$B$4:$B$6)) -> 1013472 | F31: ='02_Actual_Revenue'!E31*(1+_xlfn.XLOOKUP("Digital Services",'01_Assumptions'!$A$4:$A$6,'01_Assumptions'!$C$4:$C$6)) -> 12.24 | G31: =E31*F31 -> 12404897 | H31: =G31*'02_Actual_Revenue'!H31 -> 3721469.2 | I31: =G31-H31 -> 8683428.1 | J31: =I31/G31 -> 0.7
A32: ='02_Actual_Revenue'!A32 -> 45658 | B32: ='02_Actual_Revenue'!B32 -> P008 | C32: ='02_Actual_Revenue'!C32 -> R03 | D32: ='02_Actual_Revenue'!D32 -> 1048800 | E32: =D32*(1+_xlfn.XLOOKUP("Digital Services",'01_Assumptions'!$A$4:$A$6,'01_Assumptions'!$B$4:$B$6)) -> 1132704 | F32: ='02_Actual_Revenue'!E32*(1+_xlfn.XLOOKUP("Digital Services",'01_Assumptions'!$A$4:$A$6,'01_Assumptions'!$C$4:$C$6)) -> 12.24 | G32: =E32*F32 -> 13864297 | H32: =G32*'02_Actual_Revenue'!H32 -> 4159289.1 | I32: =G32-H32 -> 9705007.9 | J32: =I32/G32 -> 0.7
A33: ='02_Actual_Revenue'!A33 -> 45658 | B33: ='02_Actual_Revenue'!B33 -> P008 | C33: ='02_Actual_Revenue'!C33 -> R04 | D33: ='02_Actual_Revenue'!D33 -> 607200 | E33: =D33*(1+_xlfn.XLOOKUP("Digital Services",'01_Assumptions'!$A$4:$A$6,'01_Assumptions'!$B$4:$B$6)) -> 655776 | F33: ='02_Actual_Revenue'!E33*(1+_xlfn.XLOOKUP("Digital Services",'01_Assumptions'!$A$4:$A$6,'01_Assumptions'!$C$4:$C$6)) -> 12.24 | G33: =E33*F33 -> 8026698.2 | H33: =G33*'02_Actual_Revenue'!H33 -> 2408009.5 | I33: =G33-H33 -> 5618688.8 | J33: =I33/G33 -> 0.7
A34: ='02_Actual_Revenue'!A34 -> 45658 | B34: ='02_Actual_Revenue'!B34 -> P009 | C34: ='02_Actual_Revenue'!C34 -> R01 | D34: ='02_Actual_Revenue'!D34 -> 736000 | E34: =D34*(1+_xlfn.XLOOKUP("Digital Services",'01_Assumptions'!$A$4:$A$6,'01_Assumptions'!$B$4:$B$6)) -> 794880 | F34: ='02_Actual_Revenue'!E34*(1+_xlfn.XLOOKUP("Digital Services",'01_Assumptions'!$A$4:$A$6,'01_Assumptions'!$C$4:$C$6)) -> 15.3 | G34: =E34*F34 -> 12161664 | H34: =G34*'02_Actual_Revenue'!H34 -> 4256582.4 | I34: =G34-H34 -> 7905081.6 | J34: =I34/G34 -> 0.65
A35: ='02_Actual_Revenue'!A35 -> 45658 | B35: ='02_Actual_Revenue'!B35 -> P009 | C35: ='02_Actual_Revenue'!C35 -> R02 | D35: ='02_Actual_Revenue'!D35 -> 625600 | E35: =D35*(1+_xlfn.XLOOKUP("Digital Services",'01_Assumptions'!$A$4:$A$6,'01_Assumptions'!$B$4:$B$6)) -> 675648 | F35: ='02_Actual_Revenue'!E35*(1+_xlfn.XLOOKUP("Digital Services",'01_Assumptions'!$A$4:$A$6,'01_Assumptions'!$C$4:$C$6)) -> 15.3 | G35: =E35*F35 -> 10337414 | H35: =G35*'02_Actual_Revenue'!H35 -> 3618095 | I35: =G35-H35 -> 6719319.4 | J35: =I35/G35 -> 0.65
A36: ='02_Actual_Revenue'!A36 -> 45658 | B36: ='02_Actual_Revenue'!B36 -> P009 | C36: ='02_Actual_Revenue'!C36 -> R03 | D36: ='02_Actual_Revenue'!D36 -> 699200 | E36: =D36*(1+_xlfn.XLOOKUP("Digital Services",'01_Assumptions'!$A$4:$A$6,'01_Assumptions'!$B$4:$B$6)) -> 755136 | F36: ='02_Actual_Revenue'!E36*(1+_xlfn.XLOOKUP("Digital Services",'01_Assumptions'!$A$4:$A$6,'01_Assumptions'!$C$4:$C$6)) -> 15.3 | G36: =E36*F36 -> 11553581 | H36: =G36*'02_Actual_Revenue'!H36 -> 4043753.3 | I36: =G36-H36 -> 7509827.5 | J36: =I36/G36 -> 0.65
A37: ='02_Actual_Revenue'!A37 -> 45658 | B37: ='02_Actual_Revenue'!B37 -> P009 | C37: ='02_Actual_Revenue'!C37 -> R04 | D37: ='02_Actual_Revenue'!D37 -> 404800 | E37: =D37*(1+_xlfn.XLOOKUP("Digital Services",'01_Assumptions'!$A$4:$A$6,'01_Assumptions'!$B$4:$B$6)) -> 437184 | F37: ='02_Actual_Revenue'!E37*(1+_xlfn.XLOOKUP("Digital Services",'01_Assumptions'!$A$4:$A$6,'01_Assumptions'!$C$4:$C$6)) -> 15.3 | G37: =E37*F37 -> 6688915.2 | H37: =G37*'02_Actual_Revenue'!H37 -> 2341120.3 | I37: =G37-H37 -> 4347794.9 | J37: =I37/G37 -> 0.65
A38: ='02_Actual_Revenue'!A38 -> 45658 | B38: ='02_Actual_Revenue'!B38 -> P010 | C38: ='02_Actual_Revenue'!C38 -> R01 | D38: ='02_Actual_Revenue'!D38 -> 828000 | E38: =D38*(1+_xlfn.XLOOKUP("Digital Services",'01_Assumptions'!$A$4:$A$6,'01_Assumptions'!$B$4:$B$6)) -> 894240 | F38: ='02_Actual_Revenue'!E38*(1+_xlfn.XLOOKUP("Digital Services",'01_Assumptions'!$A$4:$A$6,'01_Assumptions'!$C$4:$C$6)) -> 8.16 | G38: =E38*F38 -> 7296998.4 | H38: =G38*'02_Actual_Revenue'!H38 -> 1094549.8 | I38: =G38-H38 -> 6202448.6 | J38: =I38/G38 -> 0.85
A39: ='02_Actual_Revenue'!A39 -> 45658 | B39: ='02_Actual_Revenue'!B39 -> P010 | C39: ='02_Actual_Revenue'!C39 -> R02 | D39: ='02_Actual_Revenue'!D39 -> 703800 | E39: =D39*(1+_xlfn.XLOOKUP("Digital Services",'01_Assumptions'!$A$4:$A$6,'01_Assumptions'!$B$4:$B$6)) -> 760104 | F39: ='02_Actual_Revenue'!E39*(1+_xlfn.XLOOKUP("Digital Services",'01_Assumptions'!$A$4:$A$6,'01_Assumptions'!$C$4:$C$6)) -> 8.16 | G39: =E39*F39 -> 6202448.6 | H39: =G39*'02_Actual_Revenue'!H39 -> 930367.3 | I39: =G39-H39 -> 5272081.3 | J39: =I39/G39 -> 0.85
A40: ='02_Actual_Revenue'!A40 -> 45658 | B40: ='02_Actual_Revenue'!B40 -> P010 | C40: ='02_Actual_Revenue'!C40 -> R03 | D40: ='02_Actual_Revenue'!D40 -> 786600 | E40: =D40*(1+_xlfn.XLOOKUP("Digital Services",'01_Assumptions'!$A$4:$A$6,'01_Assumptions'!$B$4:$B$6)) -> 849528 | F40: ='02_Actual_Revenue'!E40*(1+_xlfn.XLOOKUP("Digital Services",'01_Assumptions'!$A$4:$A$6,'01_Assumptions'!$C$4:$C$6)) -> 8.16 | G40: =E40*F40 -> 6932148.5 | H40: =G40*'02_Actual_Revenue'!H40 -> 1039822.3 | I40: =G40-H40 -> 5892326.2 | J40: =I40/G40 -> 0.85
A41: ='02_Actual_Revenue'!A41 -> 45658 | B41: ='02_Actual_Revenue'!B41 -> P010 | C41: ='02_Actual_Revenue'!C41 -> R04 | D41: ='02_Actual_Revenue'!D41 -> 455400 | E41: =D41*(1+_xlfn.XLOOKUP("Digital Services",'01_Assumptions'!$A$4:$A$6,'01_Assumptions'!$B$4:$B$6)) -> 491832 | F41: ='02_Actual_Revenue'!E41*(1+_xlfn.XLOOKUP("Digital Services",'01_Assumptions'!$A$4:$A$6,'01_Assumptions'!$C$4:$C$6)) -> 8.16 | G41: =E41*F41 -> 4013349.1 | H41: =G41*'02_Actual_Revenue'!H41 -> 602002.37 | I41: =G41-H41 -> 3411346.8 | J41: =I41/G41 -> 0.85
A42: ='02_Actual_Revenue'!A42 -> 45689 | B42: ='02_Actual_Revenue'!B42 -> P001 | C42: ='02_Actual_Revenue'!C42 -> R01 | D42: ='02_Actual_Revenue'!D42 -> 225000 | E42: =D42*(1+_xlfn.XLOOKUP("Devices",'01_Assumptions'!$A$4:$A$6,'01_Assumptions'!$B$4:$B$6)) -> 238500 | F42: ='02_Actual_Revenue'!E42*(1+_xlfn.XLOOKUP("Devices",'01_Assumptions'!$A$4:$A$6,'01_Assumptions'!$C$4:$C$6)) -> 712.98 | G42: =E42*F42 -> 170045730 | H42: =G42*'02_Actual_Revenue'!H42 -> 1.0542835e+08 | I42: =G42-H42 -> 64617377 | J42: =I42/G42 -> 0.38
A43: ='02_Actual_Revenue'!A43 -> 45689 | B43: ='02_Actual_Revenue'!B43 -> P001 | C43: ='02_Actual_Revenue'!C43 -> R02 | D43: ='02_Actual_Revenue'!D43 -> 191250 | E43: =D43*(1+_xlfn.XLOOKUP("Devices",'01_Assumptions'!$A$4:$A$6,'01_Assumptions'!$B$4:$B$6)) -> 202725 | F43: ='02_Actual_Revenue'!E43*(1+_xlfn.XLOOKUP("Devices",'01_Assumptions'!$A$4:$A$6,'01_Assumptions'!$C$4:$C$6)) -> 712.98 | G43: =E43*F43 -> 1.4453887e+08 | H43: =G43*'02_Actual_Revenue'!H43 -> 89614100 | I43: =G43-H43 -> 54924771 | J43: =I43/G43 -> 0.38
A44: ='02_Actual_Revenue'!A44 -> 45689 | B44: ='02_Actual_Revenue'!B44 -> P001 | C44: ='02_Actual_Revenue'!C44 -> R03 | D44: ='02_Actual_Revenue'!D44 -> 213750 | E44: =D44*(1+_xlfn.XLOOKUP("Devices",'01_Assumptions'!$A$4:$A$6,'01_Assumptions'!$B$4:$B$6)) -> 226575 | F44: ='02_Actual_Revenue'!E44*(1+_xlfn.XLOOKUP("Devices",'01_Assumptions'!$A$4:$A$6,'01_Assumptions'!$C$4:$C$6)) -> 712.98 | G44: =E44*F44 -> 1.6154344e+08 | H44: =G44*'02_Actual_Revenue'!H44 -> 1.0015693e+08 | I44: =G44-H44 -> 61386509 | J44: =I44/G44 -> 0.38
A45: ='02_Actual_Revenue'!A45 -> 45689 | B45: ='02_Actual_Revenue'!B45 -> P001 | C45: ='02_Actual_Revenue'!C45 -> R04 | D45: ='02_Actual_Revenue'!D45 -> 123750 | E45: =D45*(1+_xlfn.XLOOKUP("Devices",'01_Assumptions'!$A$4:$A$6,'01_Assumptions'!$B$4:$B$6)) -> 131175 | F45: ='02_Actual_Revenue'!E45*(1+_xlfn.XLOOKUP("Devices",'01_Assumptions'!$A$4:$A$6,'01_Assumptions'!$C$4:$C$6)) -> 712.98 | G45: =E45*F45 -> 93525152 | H45: =G45*'02_Actual_Revenue'!H45 -> 57985594 | I45: =G45-H45 -> 35539558 | J45: =I45/G45 -> 0.38
A46: ='02_Actual_Revenue'!A46 -> 45689 | B46: ='02_Actual_Revenue'!B46 -> P002 | C46: ='02_Actual_Revenue'!C46 -> R01 | D46: ='02_Actual_Revenue'!D46 -> 108000 | E46: =D46*(1+_xlfn.XLOOKUP("Devices",'01_Assumptions'!$A$4:$A$6,'01_Assumptions'!$B$4:$B$6)) -> 114480 | F46: ='02_Actual_Revenue'!E46*(1+_xlfn.XLOOKUP("Devices",'01_Assumptions'!$A$4:$A$6,'01_Assumptions'!$C$4:$C$6)) -> 1018.98 | G46: =E46*F46 -> 1.1665283e+08 | H46: =G46*'02_Actual_Revenue'!H46 -> 67658642 | I46: =G46-H46 -> 48994189 | J46: =I46/G46 -> 0.42
A47: ='02_Actual_Revenue'!A47 -> 45689 | B47: ='02_Actual_Revenue'!B47 -> P002 | C47: ='02_Actual_Revenue'!C47 -> R02 | D47: ='02_Actual_Revenue'!D47 -> 91800 | E47: =D47*(1+_xlfn.XLOOKUP("Devices",'01_Assumptions'!$A$4:$A$6,'01_Assumptions'!$B$4:$B$6)) -> 97308 | F47: ='02_Actual_Revenue'!E47*(1+_xlfn.XLOOKUP("Devices",'01_Assumptions'!$A$4:$A$6,'01_Assumptions'!$C$4:$C$6)) -> 1018.98 | G47: =E47*F47 -> 99154906 | H47: =G47*'02_Actual_Revenue'!H47 -> 57509845 | I47: =G47-H47 -> 41645060 | J47: =I47/G47 -> 0.42
A48: ='02_Actual_Revenue'!A48 -> 45689 | B48: ='02_Actual_Revenue'!B48 -> P002 | C48: ='02_Actual_Revenue'!C48 -> R03 | D48: ='02_Actual_Revenue'!D48 -> 102600 | E48: =D48*(1+_xlfn.XLOOKUP("Devices",'01_Assumptions'!$A$4:$A$6,'01_Assumptions'!$B$4:$B$6)) -> 108756 | F48: ='02_Actual_Revenue'!E48*(1+_xlfn.XLOOKUP("Devices",'01_Assumptions'!$A$4:$A$6,'01_Assumptions'!$C$4:$C$6)) -> 1018.98 | G48: =E48*F48 -> 1.1082019e+08 | H48: =G48*'02_Actual_Revenue'!H48 -> 64275710 | I48: =G48-H48 -> 46544479 | J48: =I48/G48 -> 0.42
A49: ='02_Actual_Revenue'!A49 -> 45689 | B49: ='02_Actual_Revenue'!B49 -> P002 | C49: ='02_Actual_Revenue'!C49 -> R04 | D49: ='02_Actual_Revenue'!D49 -> 59400 | E49: =D49*(1+_xlfn.XLOOKUP("Devices",'01_Assumptions'!$A$4:$A$6,'01_Assumptions'!$B$4:$B$6)) -> 62964 | F49: ='02_Actual_Revenue'!E49*(1+_xlfn.XLOOKUP("Devices",'01_Assumptions'!$A$4:$A$6,'01_Assumptions'!$C$4:$C$6)) -> 1018.98 | G49: =E49*F49 -> 64159057 | H49: =G49*'02_Actual_Revenue'!H49 -> 37212253 | I49: =G49-H49 -> 26946804 | J49: =I49/G49 -> 0.42
A50: ='02_Actual_Revenue'!A50 -> 45689 | B50: ='02_Actual_Revenue'!B50 -> P003 | C50: ='02_Actual_Revenue'!C50 -> R01 | D50: ='02_Actual_Revenue'!D50 -> 126000 | E50: =D50*(1+_xlfn.XLOOKUP("Devices",'01_Assumptions'!$A$4:$A$6,'01_Assumptions'!$B$4:$B$6)) -> 133560 | F50: ='02_Actual_Revenue'!E50*(1+_xlfn.XLOOKUP("Devices",'01_Assumptions'!$A$4:$A$6,'01_Assumptions'!$C$4:$C$6)) -> 559.98 | G50: =E50*F50 -> 74790929 | H50: =G50*'02_Actual_Revenue'!H50 -> 44874557 | I50: =G50-H50 -> 29916372 | J50: =I50/G50 -> 0.4
A51: ='02_Actual_Revenue'!A51 -> 45689 | B51: ='02_Actual_Revenue'!B51 -> P003 | C51: ='02_Actual_Revenue'!C51 -> R02 | D51: ='02_Actual_Revenue'!D51 -> 107100 | E51: =D51*(1+_xlfn.XLOOKUP("Devices",'01_Assumptions'!$A$4:$A$6,'01_Assumptions'!$B$4:$B$6)) -> 113526 | F51: ='02_Actual_Revenue'!E51*(1+_xlfn.XLOOKUP("Devices",'01_Assumptions'!$A$4:$A$6,'01_Assumptions'!$C$4:$C$6)) -> 559.98 | G51: =E51*F51 -> 63572289 | H51: =G51*'02_Actual_Revenue'!H51 -> 38143374 | I51: =G51-H51 -> 25428916 | J51: =I51/G51 -> 0.4
A52: ='02_Actual_Revenue'!A52 -> 45689 | B52: ='02_Actual_Revenue'!B52 -> P003 | C52: ='02_Actual_Revenue'!C52 -> R03 | D52: ='02_Actual_Revenue'!D52 -> 119700 | E52: =D52*(1+_xlfn.XLOOKUP("Devices",'01_Assumptions'!$A$4:$A$6,'01_Assumptions'!$B$4:$B$6)) -> 126882 | F52: ='02_Actual_Revenue'!E52*(1+_xlfn.XLOOKUP("Devices",'01_Assumptions'!$A$4:$A$6,'01_Assumptions'!$C$4:$C$6)) -> 559.98 | G52: =E52*F52 -> 71051382 | H52: =G52*'02_Actual_Revenue'!H52 -> 42630829 | I52: =G52-H52 -> 28420553 | J52: =I52/G52 -> 0.4
A53: ='02_Actual_Revenue'!A53 -> 45689 | B53: ='02_Actual_Revenue'!B53 -> P003 | C53: ='02_Actual_Revenue'!C53 -> R04 | D53: ='02_Actual_Revenue'!D53 -> 69300 | E53: =D53*(1+_xlfn.XLOOKUP("Devices",'01_Assumptions'!$A$4:$A$6,'01_Assumptions'!$B$4:$B$6)) -> 73458 | F53: ='02_Actual_Revenue'!E53*(1+_xlfn.XLOOKUP("Devices",'01_Assumptions'!$A$4:$A$6,'01_Assumptions'!$C$4:$C$6)) -> 559.98 | G53: =E53*F53 -> 41135011 | H53: =G53*'02_Actual_Revenue'!H53 -> 24681007 | I53: =G53-H53 -> 16454004 | J53: =I53/G53 -> 0.4
... A61: ='02_Actual_Revenue'!A61 -> 45689 | B61: ='02_Actual_Revenue'!B61 -> P005 | C61: ='02_Actual_Revenue'!C61 -> R04 | D61: ='02_Actual_Revenue'!D61 -> 89100 | E61: =D61*(1+_xlfn.XLOOKUP("Devices",'01_Assumptions'!$A$4:$A$6,'01_Assumptions'!$B$4:$B$6)) -> 94446 | F61: ='02_Actual_Revenue'!E61*(1+_xlfn.XLOOKUP("Devices",'01_Assumptions'!$A$4:$A$6,'01_Assumptions'!$C$4:$C$6)) -> 304.98 | G61: =E61*F61 -> 28804141 | H61: =G61*'02_Actual_Revenue'!H61 -> 14402071 | I61: =G61-H61 -> 14402071 | J61: =I61/G61 -> 0.5
A62: ='02_Actual_Revenue'!A62 -> 45689 | B62: ='02_Actual_Revenue'!B62 -> P006 | C62: ='02_Actual_Revenue'!C62 -> R01 | D62: ='02_Actual_Revenue'!D62 -> 540000 | E62: =D62*(1+_xlfn.XLOOKUP("Cloud & Software",'01_Assumptions'!$A$4:$A$6,'01_Assumptions'!$B$4:$B$6)) -> 594000 | F62: ='02_Actual_Revenue'!E62*(1+_xlfn.XLOOKUP("Cloud & Software",'01_Assumptions'!$A$4:$A$6,'01_Assumptions'!$C$4:$C$6)) -> 40.17 | G62: =E62*F62 -> 23860980 | H62: =G62*'02_Actual_Revenue'!H62 -> 5965245 | I62: =G62-H62 -> 17895735 | J62: =I62/G62 -> 0.75
A63: ='02_Actual_Revenue'!A63 -> 45689 | B63: ='02_Actual_Revenue'!B63 -> P006 | C63: ='02_Actual_Revenue'!C63 -> R02 | D63: ='02_Actual_Revenue'!D63 -> 459000 | E63: =D63*(1+_xlfn.XLOOKUP("Cloud & Software",'01_Assumptions'!$A$4:$A$6,'01_Assumptions'!$B$4:$B$6)) -> 504900 | F63: ='02_Actual_Revenue'!E63*(1+_xlfn.XLOOKUP("Cloud & Software",'01_Assumptions'!$A$4:$A$6,'01_Assumptions'!$C$4:$C$6)) -> 40.17 | G63: =E63*F63 -> 20281833 | H63: =G63*'02_Actual_Revenue'!H63 -> 5070458.3 | I63: =G63-H63 -> 15211375 | J63: =I63/G63 -> 0.75
A64: ='02_Actual_Revenue'!A64 -> 45689 | B64: ='02_Actual_Revenue'!B64 -> P006 | C64: ='02_Actual_Revenue'!C64 -> R03 | D64: ='02_Actual_Revenue'!D64 -> 513000 | E64: =D64*(1+_xlfn.XLOOKUP("Cloud & Software",'01_Assumptions'!$A$4:$A$6,'01_Assumptions'!$B$4:$B$6)) -> 564300 | F64: ='02_Actual_Revenue'!E64*(1+_xlfn.XLOOKUP("Cloud & Software",'01_Assumptions'!$A$4:$A$6,'01_Assumptions'!$C$4:$C$6)) -> 40.17 | G64: =E64*F64 -> 22667931 | H64: =G64*'02_Actual_Revenue'!H64 -> 5666982.8 | I64: =G64-H64 -> 17000948 | J64: =I64/G64 -> 0.75
A65: ='02_Actual_Revenue'!A65 -> 45689 | B65: ='02_Actual_Revenue'!B65 -> P006 | C65: ='02_Actual_Revenue'!C65 -> R04 | D65: ='02_Actual_Revenue'!D65 -> 297000 | E65: =D65*(1+_xlfn.XLOOKUP("Cloud & Software",'01_Assumptions'!$A$4:$A$6,'01_Assumptions'!$B$4:$B$6)) -> 326700 | F65: ='02_Actual_Revenue'!E65*(1+_xlfn.XLOOKUP("Cloud & Software",'01_Assumptions'!$A$4:$A$6,'01_Assumptions'!$C$4:$C$6)) -> 40.17 | G65: =E65*F65 -> 13123539 | H65: =G65*'02_Actual_Revenue'!H65 -> 3280884.8 | I65: =G65-H65 -> 9842654.2 | J65: =I65/G65 -> 0.75
A66: ='02_Actual_Revenue'!A66 -> 45689 | B66: ='02_Actual_Revenue'!B66 -> P007 | C66: ='02_Actual_Revenue'!C66 -> R01 | D66: ='02_Actual_Revenue'!D66 -> 360000 | E66: =D66*(1+_xlfn.XLOOKUP("Cloud & Software",'01_Assumptions'!$A$4:$A$6,'01_Assumptions'!$B$4:$B$6)) -> 396000 | F66: ='02_Actual_Revenue'!E66*(1+_xlfn.XLOOKUP("Cloud & Software",'01_Assumptions'!$A$4:$A$6,'01_Assumptions'!$C$4:$C$6)) -> 24.72 | G66: =E66*F66 -> 9789120 | H66: =G66*'02_Actual_Revenue'!H66 -> 1957824 | I66: =G66-H66 -> 7831296 | J66: =I66/G66 -> 0.8
A67: ='02_Actual_Revenue'!A67 -> 45689 | B67: ='02_Actual_Revenue'!B67 -> P007 | C67: ='02_Actual_Revenue'!C67 -> R02 | D67: ='02_Actual_Revenue'!D67 -> 306000 | E67: =D67*(1+_xlfn.XLOOKUP("Cloud & Software",'01_Assumptions'!$A$4:$A$6,'01_Assumptions'!$B$4:$B$6)) -> 336600 | F67: ='02_Actual_Revenue'!E67*(1+_xlfn.XLOOKUP("Cloud & Software",'01_Assumptions'!$A$4:$A$6,'01_Assumptions'!$C$4:$C$6)) -> 24.72 | G67: =E67*F67 -> 8320752 | H67: =G67*'02_Actual_Revenue'!H67 -> 1664150.4 | I67: =G67-H67 -> 6656601.6 | J67: =I67/G67 -> 0.8
A68: ='02_Actual_Revenue'!A68 -> 45689 | B68: ='02_Actual_Revenue'!B68 -> P007 | C68: ='02_Actual_Revenue'!C68 -> R03 | D68: ='02_Actual_Revenue'!D68 -> 342000 | E68: =D68*(1+_xlfn.XLOOKUP("Cloud & Software",'01_Assumptions'!$A$4:$A$6,'01_Assumptions'!$B$4:$B$6)) -> 376200 | F68: ='02_Actual_Revenue'!E68*(1+_xlfn.XLOOKUP("Cloud & Software",'01_Assumptions'!$A$4:$A$6,'01_Assumptions'!$C$4:$C$6)) -> 24.72 | G68: =E68*F68 -> 9299664 | H68: =G68*'02_Actual_Revenue'!H68 -> 1859932.8 | I68: =G68-H68 -> 7439731.2 | J68: =I68/G68 -> 0.8
A69: ='02_Actual_Revenue'!A69 -> 45689 | B69: ='02_Actual_Revenue'!B69 -> P007 | C69: ='02_Actual_Revenue'!C69 -> R04 | D69: ='02_Actual_Revenue'!D69 -> 198000 | E69: =D69*(1+_xlfn.XLOOKUP("Cloud & Software",'01_Assumptions'!$A$4:$A$6,'01_Assumptions'!$B$4:$B$6)) -> 217800 | F69: ='02_Actual_Revenue'!E69*(1+_xlfn.XLOOKUP("Cloud & Software",'01_Assumptions'!$A$4:$A$6,'01_Assumptions'!$C$4:$C$6)) -> 24.72 | G69: =E69*F69 -> 5384016 | H69: =G69*'02_Actual_Revenue'!H69 -> 1076803.2 | I69: =G69-H69 -> 4307212.8 | J69: =I69/G69 -> 0.8
A70: ='02_Actual_Revenue'!A70 -> 45689 | B70: ='02_Actual_Revenue'!B70 -> P008 | C70: ='02_Actual_Revenue'!C70 -> R01 | D70: ='02_Actual_Revenue'!D70 -> 1080000 | E70: =D70*(1+_xlfn.XLOOKUP("Digital Services",'01_Assumptions'!$A$4:$A$6,'01_Assumptions'!$B$4:$B$6)) -> 1166400 | F70: ='02_Actual_Revenue'!E70*(1+_xlfn.XLOOKUP("Digital Services",'01_Assumptions'!$A$4:$A$6,'01_Assumptions'!$C$4:$C$6)) -> 12.24 | G70: =E70*F70 -> 14276736 | H70: =G70*'02_Actual_Revenue'!H70 -> 4283020.8 | I70: =G70-H70 -> 9993715.2 | J70: =I70/G70 -> 0.7
A71: ='02_Actual_Revenue'!A71 -> 45689 | B71: ='02_Actual_Revenue'!B71 -> P008 | C71: ='02_Actual_Revenue'!C71 -> R02 | D71: ='02_Actual_Revenue'!D71 -> 918000 | E71: =D71*(1+_xlfn.XLOOKUP("Digital Services",'01_Assumptions'!$A$4:$A$6,'01_Assumptions'!$B$4:$B$6)) -> 991440 | F71: ='02_Actual_Revenue'!E71*(1+_xlfn.XLOOKUP("Digital Services",'01_Assumptions'!$A$4:$A$6,'01_Assumptions'!$C$4:$C$6)) -> 12.24 | G71: =E71*F71 -> 12135226 | H71: =G71*'02_Actual_Revenue'!H71 -> 3640567.7 | I71: =G71-H71 -> 8494657.9 | J71: =I71/G71 -> 0.7
A72: ='02_Actual_Revenue'!A72 -> 45689 | B72: ='02_Actual_Revenue'!B72 -> P008 | C72: ='02_Actual_Revenue'!C72 -> R03 | D72: ='02_Actual_Revenue'!D72 -> 1026000 | E72: =D72*(1+_xlfn.XLOOKUP("Digital Services",'01_Assumptions'!$A$4:$A$6,'01_Assumptions'!$B$4:$B$6)) -> 1108080 | F72: ='02_Actual_Revenue'!E72*(1+_xlfn.XLOOKUP("Digital Services",'01_Assumptions'!$A$4:$A$6,'01_Assumptions'!$C$4:$C$6)) -> 12.24 | G72: =E72*F72 -> 13562899 | H72: =G72*'02_Actual_Revenue'!H72 -> 4068869.8 | I72: =G72-H72 -> 9494029.4 | J72: =I72/G72 -> 0.7
A73: ='02_Actual_Revenue'!A73 -> 45689 | B73: ='02_Actual_Revenue'!B73 -> P008 | C73: ='02_Actual_Revenue'!C73 -> R04 | D73: ='02_Actual_Revenue'!D73 -> 594000 | E73: =D73*(1+_xlfn.XLOOKUP("Digital Services",'01_Assumptions'!$A$4:$A$6,'01_Assumptions'!$B$4:$B$6)) -> 641520 | F73: ='02_Actual_Revenue'!E73*(1+_xlfn.XLOOKUP("Digital Services",'01_Assumptions'!$A$4:$A$6,'01_Assumptions'!$C$4:$C$6)) -> 12.24 | G73: =E73*F73 -> 7852204.8 | H73: =G73*'02_Actual_Revenue'!H73 -> 2355661.4 | I73: =G73-H73 -> 5496543.4 | J73: =I73/G73 -> 0.7
A74: ='02_Actual_Revenue'!A74 -> 45689 | B74: ='02_Actual_Revenue'!B74 -> P009 | C74: ='02_Actual_Revenue'!C74 -> R01 | D74: ='02_Actual_Revenue'!D74 -> 720000 | E74: =D74*(1+_xlfn.XLOOKUP("Digital Services",'01_Assumptions'!$A$4:$A$6,'01_Assumptions'!$B$4:$B$6)) -> 777600 | F74: ='02_Actual_Revenue'!E74*(1+_xlfn.XLOOKUP("Digital Services",'01_Assumptions'!$A$4:$A$6,'01_Assumptions'!$C$4:$C$6)) -> 15.3 | G74: =E74*F74 -> 11897280 | H74: =G74*'02_Actual_Revenue'!H74 -> 4164048 | I74: =G74-H74 -> 7733232 | J74: =I74/G74 -> 0.65
A75: ='02_Actual_Revenue'!A75 -> 45689 | B75: ='02_Actual_Revenue'!B75 -> P009 | C75: ='02_Actual_Revenue'!C75 -> R02 | D75: ='02_Actual_Revenue'!D75 -> 612000 | E75: =D75*(1+_xlfn.XLOOKUP("Digital Services",'01_Assumptions'!$A$4:$A$6,'01_Assumptions'!$B$4:$B$6)) -> 660960 | F75: ='02_Actual_Revenue'!E75*(1+_xlfn.XLOOKUP("Digital Services",'01_Assumptions'!$A$4:$A$6,'01_Assumptions'!$C$4:$C$6)) -> 15.3 | G75: =E75*F75 -> 10112688 | H75: =G75*'02_Actual_Revenue'!H75 -> 3539440.8 | I75: =G75-H75 -> 6573247.2 | J75: =I75/G75 -> 0.65
A76: ='02_Actual_Revenue'!A76 -> 45689 | B76: ='02_Actual_Revenue'!B76 -> P009 | C76: ='02_Actual_Revenue'!C76 -> R03 | D76: ='02_Actual_Revenue'!D76 -> 684000 | E76: =D76*(1+_xlfn.XLOOKUP("Digital Services",'01_Assumptions'!$A$4:$A$6,'01_Assumptions'!$B$4:$B$6)) -> 738720 | F76: ='02_Actual_Revenue'!E76*(1+_xlfn.XLOOKUP("Digital Services",'01_Assumptions'!$A$4:$A$6,'01_Assumptions'!$C$4:$C$6)) -> 15.3 | G76: =E76*F76 -> 11302416 | H76: =G76*'02_Actual_Revenue'!H76 -> 3955845.6 | I76: =G76-H76 -> 7346570.4 | J76: =I76/G76 -> 0.65
A77: ='02_Actual_Revenue'!A77 -> 45689 | B77: ='02_Actual_Revenue'!B77 -> P009 | C77: ='02_Actual_Revenue'!C77 -> R04 | D77: ='02_Actual_Revenue'!D77 -> 396000 | E77: =D77*(1+_xlfn.XLOOKUP("Digital Services",'01_Assumptions'!$A$4:$A$6,'01_Assumptions'!$B$4:$B$6)) -> 427680 | F77: ='02_Actual_Revenue'!E77*(1+_xlfn.XLOOKUP("Digital Services",'01_Assumptions'!$A$4:$A$6,'01_Assumptions'!$C$4:$C$6)) -> 15.3 | G77: =E77*F77 -> 6543504 | H77: =G77*'02_Actual_Revenue'!H77 -> 2290226.4 | I77: =G77-H77 -> 4253277.6 | J77: =I77/G77 -> 0.65
A78: ='02_Actual_Revenue'!A78 -> 45689 | B78: ='02_Actual_Revenue'!B78 -> P010 | C78: ='02_Actual_Revenue'!C78 -> R01 | D78: ='02_Actual_Revenue'!D78 -> 810000 | E78: =D78*(1+_xlfn.XLOOKUP("Digital Services",'01_Assumptions'!$A$4:$A$6,'01_Assumptions'!$B$4:$B$6)) -> 874800 | F78: ='02_Actual_Revenue'!E78*(1+_xlfn.XLOOKUP("Digital Services",'01_Assumptions'!$A$4:$A$6,'01_Assumptions'!$C$4:$C$6)) -> 8.16 | G78: =E78*F78 -> 7138368 | H78: =G78*'02_Actual_Revenue'!H78 -> 1070755.2 | I78: =G78-H78 -> 6067612.8 | J78: =I78/G78 -> 0.85
A79: ='02_Actual_Revenue'!A79 -> 45689 | B79: ='02_Actual_Revenue'!B79 -> P010 | C79: ='02_Actual_Revenue'!C79 -> R02 | D79: ='02_Actual_Revenue'!D79 -> 688500 | E79: =D79*(1+_xlfn.XLOOKUP("Digital Services",'01_Assumptions'!$A$4:$A$6,'01_Assumptions'!$B$4:$B$6)) -> 743580 | F79: ='02_Actual_Revenue'!E79*(1+_xlfn.XLOOKUP("Digital Services",'01_Assumptions'!$A$4:$A$6,'01_Assumptions'!$C$4:$C$6)) -> 8.16 | G79: =E79*F79 -> 6067612.8 | H79: =G79*'02_Actual_Revenue'!H79 -> 910141.92 | I79: =G79-H79 -> 5157470.9 | J79: =I79/G79 -> 0.85
A80: ='02_Actual_Revenue'!A80 -> 45689 | B80: ='02_Actual_Revenue'!B80 -> P010 | C80: ='02_Actual_Revenue'!C80 -> R03 | D80: ='02_Actual_Revenue'!D80 -> 769500 | E80: =D80*(1+_xlfn.XLOOKUP("Digital Services",'01_Assumptions'!$A$4:$A$6,'01_Assumptions'!$B$4:$B$6)) -> 831060 | F80: ='02_Actual_Revenue'!E80*(1+_xlfn.XLOOKUP("Digital Services",'01_Assumptions'!$A$4:$A$6,'01_Assumptions'!$C$4:$C$6)) -> 8.16 | G80: =E80*F80 -> 6781449.6 | H80: =G80*'02_Actual_Revenue'!H80 -> 1017217.4 | I80: =G80-H80 -> 5764232.2 | J80: =I80/G80 -> 0.85
A81: ='02_Actual_Revenue'!A81 -> 45689 | B81: ='02_Actual_Revenue'!B81 -> P010 | C81: ='02_Actual_Revenue'!C81 -> R04 | D81: ='02_Actual_Revenue'!D81 -> 445500 | E81: =D81*(1+_xlfn.XLOOKUP("Digital Services",'01_Assumptions'!$A$4:$A$6,'01_Assumptions'!$B$4:$B$6)) -> 481140 | F81: ='02_Actual_Revenue'!E81*(1+_xlfn.XLOOKUP("Digital Services",'01_Assumptions'!$A$4:$A$6,'01_Assumptions'!$C$4:$C$6)) -> 8.16 | G81: =E81*F81 -> 3926102.4 | H81: =G81*'02_Actual_Revenue'!H81 -> 588915.36 | I81: =G81-H81 -> 3337187 | J81: =I81/G81 -> 0.85
A82: ='02_Actual_Revenue'!A82 -> 45717 | B82: ='02_Actual_Revenue'!B82 -> P001 | C82: ='02_Actual_Revenue'!C82 -> R01 | D82: ='02_Actual_Revenue'!D82 -> 240000 | E82: =D82*(1+_xlfn.XLOOKUP("Devices",'01_Assumptions'!$A$4:$A$6,'01_Assumptions'!$B$4:$B$6)) -> 254400 | F82: ='02_Actual_Revenue'!E82*(1+_xlfn.XLOOKUP("Devices",'01_Assumptions'!$A$4:$A$6,'01_Assumptions'!$C$4:$C$6)) -> 712.98 | G82: =E82*F82 -> 181382112 | H82: =G82*'02_Actual_Revenue'!H82 -> 1.1245691e+08 | I82: =G82-H82 -> 68925203 | J82: =I82/G82 -> 0.38
A83: ='02_Actual_Revenue'!A83 -> 45717 | B83: ='02_Actual_Revenue'!B83 -> P001 | C83: ='02_Actual_Revenue'!C83 -> R02 | D83: ='02_Actual_Revenue'!D83 -> 204000 | E83: =D83*(1+_xlfn.XLOOKUP("Devices",'01_Assumptions'!$A$4:$A$6,'01_Assumptions'!$B$4:$B$6)) -> 216240 | F83: ='02_Actual_Revenue'!E83*(1+_xlfn.XLOOKUP("Devices",'01_Assumptions'!$A$4:$A$6,'01_Assumptions'!$C$4:$C$6)) -> 712.98 | G83: =E83*F83 -> 1.541748e+08 | H83: =G83*'02_Actual_Revenue'!H83 -> 95588373 | I83: =G83-H83 -> 58586422 | J83: =I83/G83 -> 0.38
A84: ='02_Actual_Revenue'!A84 -> 45717 | B84: ='02_Actual_Revenue'!B84 -> P001 | C84: ='02_Actual_Revenue'!C84 -> R03 | D84: ='02_Actual_Revenue'!D84 -> 228000 | E84: =D84*(1+_xlfn.XLOOKUP("Devices",'01_Assumptions'!$A$4:$A$6,'01_Assumptions'!$B$4:$B$6)) -> 241680 | F84: ='02_Actual_Revenue'!E84*(1+_xlfn.XLOOKUP("Devices",'01_Assumptions'!$A$4:$A$6,'01_Assumptions'!$C$4:$C$6)) -> 712.98 | G84: =E84*F84 -> 1.7231301e+08 | H84: =G84*'02_Actual_Revenue'!H84 -> 1.0683406e+08 | I84: =G84-H84 -> 65478942 | J84: =I84/G84 -> 0.38
A85: ='02_Actual_Revenue'!A85 -> 45717 | B85: ='02_Actual_Revenue'!B85 -> P001 | C85: ='02_Actual_Revenue'!C85 -> R04 | D85: ='02_Actual_Revenue'!D85 -> 132000 | E85: =D85*(1+_xlfn.XLOOKUP("Devices",'01_Assumptions'!$A$4:$A$6,'01_Assumptions'!$B$4:$B$6)) -> 139920 | F85: ='02_Actual_Revenue'!E85*(1+_xlfn.XLOOKUP("Devices",'01_Assumptions'!$A$4:$A$6,'01_Assumptions'!$C$4:$C$6)) -> 712.98 | G85: =E85*F85 -> 99760162 | H85: =G85*'02_Actual_Revenue'!H85 -> 61851300 | I85: =G85-H85 -> 37908861 | J85: =I85/G85 -> 0.38
A86: ='02_Actual_Revenue'!A86 -> 45717 | B86: ='02_Actual_Revenue'!B86 -> P002 | C86: ='02_Actual_Revenue'!C86 -> R01 | D86: ='02_Actual_Revenue'!D86 -> 115200 | E86: =D86*(1+_xlfn.XLOOKUP("Devices",'01_Assumptions'!$A$4:$A$6,'01_Assumptions'!$B$4:$B$6)) -> 122112 | F86: ='02_Actual_Revenue'!E86*(1+_xlfn.XLOOKUP("Devices",'01_Assumptions'!$A$4:$A$6,'01_Assumptions'!$C$4:$C$6)) -> 1018.98 | G86: =E86*F86 -> 1.2442969e+08 | H86: =G86*'02_Actual_Revenue'!H86 -> 72169218 | I86: =G86-H86 -> 52260468 | J86: =I86/G86 -> 0.42
A87: ='02_Actual_Revenue'!A87 -> 45717 | B87: ='02_Actual_Revenue'!B87 -> P002 | C87: ='02_Actual_Revenue'!C87 -> R02 | D87: ='02_Actual_Revenue'!D87 -> 97920 | E87: =D87*(1+_xlfn.XLOOKUP("Devices",'01_Assumptions'!$A$4:$A$6,'01_Assumptions'!$B$4:$B$6)) -> 103795.2 | F87: ='02_Actual_Revenue'!E87*(1+_xlfn.XLOOKUP("Devices",'01_Assumptions'!$A$4:$A$6,'01_Assumptions'!$C$4:$C$6)) -> 1018.98 | G87: =E87*F87 -> 1.0576523e+08 | H87: =G87*'02_Actual_Revenue'!H87 -> 61343835 | I87: =G87-H87 -> 44421398 | J87: =I87/G87 -> 0.42
A88: ='02_Actual_Revenue'!A88 -> 45717 | B88: ='02_Actual_Revenue'!B88 -> P002 | C88: ='02_Actual_Revenue'!C88 -> R03 | D88: ='02_Actual_Revenue'!D88 -> 109440 | E88: =D88*(1+_xlfn.XLOOKUP("Devices",'01_Assumptions'!$A$4:$A$6,'01_Assumptions'!$B$4:$B$6)) -> 116006.4 | F88: ='02_Actual_Revenue'!E88*(1+_xlfn.XLOOKUP("Devices",'01_Assumptions'!$A$4:$A$6,'01_Assumptions'!$C$4:$C$6)) -> 1018.98 | G88: =E88*F88 -> 1.182082e+08 | H88: =G88*'02_Actual_Revenue'!H88 -> 68560757 | I88: =G88-H88 -> 49647445 | J88: =I88/G88 -> 0.42
A89: ='02_Actual_Revenue'!A89 -> 45717 | B89: ='02_Actual_Revenue'!B89 -> P002 | C89: ='02_Actual_Revenue'!C89 -> R04 | D89: ='02_Actual_Revenue'!D89 -> 63360 | E89: =D89*(1+_xlfn.XLOOKUP("Devices",'01_Assumptions'!$A$4:$A$6,'01_Assumptions'!$B$4:$B$6)) -> 67161.6 | F89: ='02_Actual_Revenue'!E89*(1+_xlfn.XLOOKUP("Devices",'01_Assumptions'!$A$4:$A$6,'01_Assumptions'!$C$4:$C$6)) -> 1018.98 | G89: =E89*F89 -> 68436327 | H89: =G89*'02_Actual_Revenue'!H89 -> 39693070 | I89: =G89-H89 -> 28743257 | J89: =I89/G89 -> 0.42
A90: ='02_Actual_Revenue'!A90 -> 45717 | B90: ='02_Actual_Revenue'!B90 -> P003 | C90: ='02_Actual_Revenue'!C90 -> R01 | D90: ='02_Actual_Revenue'!D90 -> 134400 | E90: =D90*(1+_xlfn.XLOOKUP("Devices",'01_Assumptions'!$A$4:$A$6,'01_Assumptions'!$B$4:$B$6)) -> 142464 | F90: ='02_Actual_Revenue'!E90*(1+_xlfn.XLOOKUP("Devices",'01_Assumptions'!$A$4:$A$6,'01_Assumptions'!$C$4:$C$6)) -> 559.98 | G90: =E90*F90 -> 79776991 | H90: =G90*'02_Actual_Revenue'!H90 -> 47866194 | I90: =G90-H90 -> 31910796 | J90: =I90/G90 -> 0.4
A91: ='02_Actual_Revenue'!A91 -> 45717 | B91: ='02_Actual_Revenue'!B91 -> P003 | C91: ='02_Actual_Revenue'!C91 -> R02 | D91: ='02_Actual_Revenue'!D91 -> 114240 | E91: =D91*(1+_xlfn.XLOOKUP("Devices",'01_Assumptions'!$A$4:$A$6,'01_Assumptions'!$B$4:$B$6)) -> 121094.4 | F91: ='02_Actual_Revenue'!E91*(1+_xlfn.XLOOKUP("Devices",'01_Assumptions'!$A$4:$A$6,'01_Assumptions'!$C$4:$C$6)) -> 559.98 | G91: =E91*F91 -> 67810442 | H91: =G91*'02_Actual_Revenue'!H91 -> 40686265 | I91: =G91-H91 -> 27124177 | J91: =I91/G91 -> 0.4
A92: ='02_Actual_Revenue'!A92 -> 45717 | B92: ='02_Actual_Revenue'!B92 -> P003 | C92: ='02_Actual_Revenue'!C92 -> R03 | D92: ='02_Actual_Revenue'!D92 -> 127680 | E92: =D92*(1+_xlfn.XLOOKUP("Devices",'01_Assumptions'!$A$4:$A$6,'01_Assumptions'!$B$4:$B$6)) -> 135340.8 | F92: ='02_Actual_Revenue'!E92*(1+_xlfn.XLOOKUP("Devices",'01_Assumptions'!$A$4:$A$6,'01_Assumptions'!$C$4:$C$6)) -> 559.98 | G92: =E92*F92 -> 75788141 | H92: =G92*'02_Actual_Revenue'!H92 -> 45472885 | I92: =G92-H92 -> 30315256 | J92: =I92/G92 -> 0.4
A93: ='02_Actual_Revenue'!A93 -> 45717 | B93: ='02_Actual_Revenue'!B93 -> P003 | C93: ='02_Actual_Revenue'!C93 -> R04 | D93: ='02_Actual_Revenue'!D93 -> 73920 | E93: =D93*(1+_xlfn.XLOOKUP("Devices",'01_Assumptions'!$A$4:$A$6,'01_Assumptions'!$B$4:$B$6)) -> 78355.2 | F93: ='02_Actual_Revenue'!E93*(1+_xlfn.XLOOKUP("Devices",'01_Assumptions'!$A$4:$A$6,'01_Assumptions'!$C$4:$C$6)) -> 559.98 | G93: =E93*F93 -> 43877345 | H93: =G93*'02_Actual_Revenue'!H93 -> 26326407 | I93: =G93-H93 -> 17550938 | J93: =I93/G93 -> 0.4
... A101: ='02_Actual_Revenue'!A101 -> 45717 | B101: ='02_Actual_Revenue'!B101 -> P005 | C101: ='02_Actual_Revenue'!C101 -> R04 | D101: ='02_Actual_Revenue'!D101 -> 95040 | E101: =D101*(1+_xlfn.XLOOKUP("Devices",'01_Assumptions'!$A$4:$A$6,'01_Assumptions'!$B$4:$B$6)) -> 100742.4 | F101: ='02_Actual_Revenue'!E101*(1+_xlfn.XLOOKUP("Devices",'01_Assumptions'!$A$4:$A$6,'01_Assumptions'!$C$4:$C$6)) -> 304.98 | G101: =E101*F101 -> 30724417 | H101: =G101*'02_Actual_Revenue'!H101 -> 15362209 | I101: =G101-H101 -> 15362209 | J101: =I101/G101 -> 0.5
A102: ='02_Actual_Revenue'!A102 -> 45717 | B102: ='02_Actual_Revenue'!B102 -> P006 | C102: ='02_Actual_Revenue'!C102 -> R01 | D102: ='02_Actual_Revenue'!D102 -> 576000 | E102: =D102*(1+_xlfn.XLOOKUP("Cloud & Software",'01_Assumptions'!$A$4:$A$6,'01_Assumptions'!$B$4:$B$6)) -> 633600 | F102: ='02_Actual_Revenue'!E102*(1+_xlfn.XLOOKUP("Cloud & Software",'01_Assumptions'!$A$4:$A$6,'01_Assumptions'!$C$4:$C$6)) -> 40.17 | G102: =E102*F102 -> 25451712 | H102: =G102*'02_Actual_Revenue'!H102 -> 6362928 | I102: =G102-H102 -> 19088784 | J102: =I102/G102 -> 0.75
A103: ='02_Actual_Revenue'!A103 -> 45717 | B103: ='02_Actual_Revenue'!B103 -> P006 | C103: ='02_Actual_Revenue'!C103 -> R02 | D103: ='02_Actual_Revenue'!D103 -> 489600 | E103: =D103*(1+_xlfn.XLOOKUP("Cloud & Software",'01_Assumptions'!$A$4:$A$6,'01_Assumptions'!$B$4:$B$6)) -> 538560 | F103: ='02_Actual_Revenue'!E103*(1+_xlfn.XLOOKUP("Cloud & Software",'01_Assumptions'!$A$4:$A$6,'01_Assumptions'!$C$4:$C$6)) -> 40.17 | G103: =E103*F103 -> 21633955 | H103: =G103*'02_Actual_Revenue'!H103 -> 5408488.8 | I103: =G103-H103 -> 16225466 | J103: =I103/G103 -> 0.75
A104: ='02_Actual_Revenue'!A104 -> 45717 | B104: ='02_Actual_Revenue'!B104 -> P006 | C104: ='02_Actual_Revenue'!C104 -> R03 | D104: ='02_Actual_Revenue'!D104 -> 547200 | E104: =D104*(1+_xlfn.XLOOKUP("Cloud & Software",'01_Assumptions'!$A$4:$A$6,'01_Assumptions'!$B$4:$B$6)) -> 601920 | F104: ='02_Actual_Revenue'!E104*(1+_xlfn.XLOOKUP("Cloud & Software",'01_Assumptions'!$A$4:$A$6,'01_Assumptions'!$C$4:$C$6)) -> 40.17 | G104: =E104*F104 -> 24179126 | H104: =G104*'02_Actual_Revenue'!H104 -> 6044781.6 | I104: =G104-H104 -> 18134345 | J104: =I104/G104 -> 0.75
A105: ='02_Actual_Revenue'!A105 -> 45717 | B105: ='02_Actual_Revenue'!B105 -> P006 | C105: ='02_Actual_Revenue'!C105 -> R04 | D105: ='02_Actual_Revenue'!D105 -> 316800 | E105: =D105*(1+_xlfn.XLOOKUP("Cloud & Software",'01_Assumptions'!$A$4:$A$6,'01_Assumptions'!$B$4:$B$6)) -> 348480 | F105: ='02_Actual_Revenue'!E105*(1+_xlfn.XLOOKUP("Cloud & Software",'01_Assumptions'!$A$4:$A$6,'01_Assumptions'!$C$4:$C$6)) -> 40.17 | G105: =E105*F105 -> 13998442 | H105: =G105*'02_Actual_Revenue'!H105 -> 3499610.4 | I105: =G105-H105 -> 10498831 | J105: =I105/G105 -> 0.75
A106: ='02_Actual_Revenue'!A106 -> 45717 | B106: ='02_Actual_Revenue'!B106 -> P007 | C106: ='02_Actual_Revenue'!C106 -> R01 | D106: ='02_Actual_Revenue'!D106 -> 384000 | E106: =D106*(1+_xlfn.XLOOKUP("Cloud & Software",'01_Assumptions'!$A$4:$A$6,'01_Assumptions'!$B$4:$B$6)) -> 422400 | F106: ='02_Actual_Revenue'!E106*(1+_xlfn.XLOOKUP("Cloud & Software",'01_Assumptions'!$A$4:$A$6,'01_Assumptions'!$C$4:$C$6)) -> 24.72 | G106: =E106*F106 -> 10441728 | H106: =G106*'02_Actual_Revenue'!H106 -> 2088345.6 | I106: =G106-H106 -> 8353382.4 | J106: =I106/G106 -> 0.8
A107: ='02_Actual_Revenue'!A107 -> 45717 | B107: ='02_Actual_Revenue'!B107 -> P007 | C107: ='02_Actual_Revenue'!C107 -> R02 | D107: ='02_Actual_Revenue'!D107 -> 326400 | E107: =D107*(1+_xlfn.XLOOKUP("Cloud & Software",'01_Assumptions'!$A$4:$A$6,'01_Assumptions'!$B$4:$B$6)) -> 359040 | F107: ='02_Actual_Revenue'!E107*(1+_xlfn.XLOOKUP("Cloud & Software",'01_Assumptions'!$A$4:$A$6,'01_Assumptions'!$C$4:$C$6)) -> 24.72 | G107: =E107*F107 -> 8875468.8 | H107: =G107*'02_Actual_Revenue'!H107 -> 1775093.8 | I107: =G107-H107 -> 7100375 | J107: =I107/G107 -> 0.8
A108: ='02_Actual_Revenue'!A108 -> 45717 | B108: ='02_Actual_Revenue'!B108 -> P007 | C108: ='02_Actual_Revenue'!C108 -> R03 | D108: ='02_Actual_Revenue'!D108 -> 364800 | E108: =D108*(1+_xlfn.XLOOKUP("Cloud & Software",'01_Assumptions'!$A$4:$A$6,'01_Assumptions'!$B$4:$B$6)) -> 401280 | F108: ='02_Actual_Revenue'!E108*(1+_xlfn.XLOOKUP("Cloud & Software",'01_Assumptions'!$A$4:$A$6,'01_Assumptions'!$C$4:$C$6)) -> 24.72 | G108: =E108*F108 -> 9919641.6 | H108: =G108*'02_Actual_Revenue'!H108 -> 1983928.3 | I108: =G108-H108 -> 7935713.3 | J108: =I108/G108 -> 0.8
A109: ='02_Actual_Revenue'!A109 -> 45717 | B109: ='02_Actual_Revenue'!B109 -> P007 | C109: ='02_Actual_Revenue'!C109 -> R04 | D109: ='02_Actual_Revenue'!D109 -> 211200 | E109: =D109*(1+_xlfn.XLOOKUP("Cloud & Software",'01_Assumptions'!$A$4:$A$6,'01_Assumptions'!$B$4:$B$6)) -> 232320 | F109: ='02_Actual_Revenue'!E109*(1+_xlfn.XLOOKUP("Cloud & Software",'01_Assumptions'!$A$4:$A$6,'01_Assumptions'!$C$4:$C$6)) -> 24.72 | G109: =E109*F109 -> 5742950.4 | H109: =G109*'02_Actual_Revenue'!H109 -> 1148590.1 | I109: =G109-H109 -> 4594360.3 | J109: =I109/G109 -> 0.8
A110: ='02_Actual_Revenue'!A110 -> 45717 | B110: ='02_Actual_Revenue'!B110 -> P008 | C110: ='02_Actual_Revenue'!C110 -> R01 | D110: ='02_Actual_Revenue'!D110 -> 1152000 | E110: =D110*(1+_xlfn.XLOOKUP("Digital Services",'01_Assumptions'!$A$4:$A$6,'01_Assumptions'!$B$4:$B$6)) -> 1244160 | F110: ='02_Actual_Revenue'!E110*(1+_xlfn.XLOOKUP("Digital Services",'01_Assumptions'!$A$4:$A$6,'01_Assumptions'!$C$4:$C$6)) -> 12.24 | G110: =E110*F110 -> 15228518 | H110: =G110*'02_Actual_Revenue'!H110 -> 4568555.5 | I110: =G110-H110 -> 10659963 | J110: =I110/G110 -> 0.7
A111: ='02_Actual_Revenue'!A111 -> 45717 | B111: ='02_Actual_Revenue'!B111 -> P008 | C111: ='02_Actual_Revenue'!C111 -> R02 | D111: ='02_Actual_Revenue'!D111 -> 979200 | E111: =D111*(1+_xlfn.XLOOKUP("Digital Services",'01_Assumptions'!$A$4:$A$6,'01_Assumptions'!$B$4:$B$6)) -> 1057536 | F111: ='02_Actual_Revenue'!E111*(1+_xlfn.XLOOKUP("Digital Services",'01_Assumptions'!$A$4:$A$6,'01_Assumptions'!$C$4:$C$6)) -> 12.24 | G111: =E111*F111 -> 12944241 | H111: =G111*'02_Actual_Revenue'!H111 -> 3883272.2 | I111: =G111-H111 -> 9060968.4 | J111: =I111/G111 -> 0.7
A112: ='02_Actual_Revenue'!A112 -> 45717 | B112: ='02_Actual_Revenue'!B112 -> P008 | C112: ='02_Actual_Revenue'!C112 -> R03 | D112: ='02_Actual_Revenue'!D112 -> 1094400 | E112: =D112*(1+_xlfn.XLOOKUP("Digital Services",'01_Assumptions'!$A$4:$A$6,'01_Assumptions'!$B$4:$B$6)) -> 1181952 | F112: ='02_Actual_Revenue'!E112*(1+_xlfn.XLOOKUP("Digital Services",'01_Assumptions'!$A$4:$A$6,'01_Assumptions'!$C$4:$C$6)) -> 12.24 | G112: =E112*F112 -> 14467092 | H112: =G112*'02_Actual_Revenue'!H112 -> 4340127.7 | I112: =G112-H112 -> 10126965 | J112: =I112/G112 -> 0.7
A113: ='02_Actual_Revenue'!A113 -> 45717 | B113: ='02_Actual_Revenue'!B113 -> P008 | C113: ='02_Actual_Revenue'!C113 -> R04 | D113: ='02_Actual_Revenue'!D113 -> 633600 | E113: =D113*(1+_xlfn.XLOOKUP("Digital Services",'01_Assumptions'!$A$4:$A$6,'01_Assumptions'!$B$4:$B$6)) -> 684288 | F113: ='02_Actual_Revenue'!E113*(1+_xlfn.XLOOKUP("Digital Services",'01_Assumptions'!$A$4:$A$6,'01_Assumptions'!$C$4:$C$6)) -> 12.24 | G113: =E113*F113 -> 8375685.1 | H113: =G113*'02_Actual_Revenue'!H113 -> 2512705.5 | I113: =G113-H113 -> 5862979.6 | J113: =I113/G113 -> 0.7
A114: ='02_Actual_Revenue'!A114 -> 45717 | B114: ='02_Actual_Revenue'!B114 -> P009 | C114: ='02_Actual_Revenue'!C114 -> R01 | D114: ='02_Actual_Revenue'!D114 -> 768000 | E114: =D114*(1+_xlfn.XLOOKUP("Digital Services",'01_Assumptions'!$A$4:$A$6,'01_Assumptions'!$B$4:$B$6)) -> 829440 | F114: ='02_Actual_Revenue'!E114*(1+_xlfn.XLOOKUP("Digital Services",'01_Assumptions'!$A$4:$A$6,'01_Assumptions'!$C$4:$C$6)) -> 15.3 | G114: =E114*F114 -> 12690432 | H114: =G114*'02_Actual_Revenue'!H114 -> 4441651.2 | I114: =G114-H114 -> 8248780.8 | J114: =I114/G114 -> 0.65
A115: ='02_Actual_Revenue'!A115 -> 45717 | B115: ='02_Actual_Revenue'!B115 -> P009 | C115: ='02_Actual_Revenue'!C115 -> R02 | D115: ='02_Actual_Revenue'!D115 -> 652800 | E115: =D115*(1+_xlfn.XLOOKUP("Digital Services",'01_Assumptions'!$A$4:$A$6,'01_Assumptions'!$B$4:$B$6)) -> 705024 | F115: ='02_Actual_Revenue'!E115*(1+_xlfn.XLOOKUP("Digital Services",'01_Assumptions'!$A$4:$A$6,'01_Assumptions'!$C$4:$C$6)) -> 15.3 | G115: =E115*F115 -> 10786867 | H115: =G115*'02_Actual_Revenue'!H115 -> 3775403.5 | I115: =G115-H115 -> 7011463.7 | J115: =I115/G115 -> 0.65
A116: ='02_Actual_Revenue'!A116 -> 45717 | B116: ='02_Actual_Revenue'!B116 -> P009 | C116: ='02_Actual_Revenue'!C116 -> R03 | D116: ='02_Actual_Revenue'!D116 -> 729600 | E116: =D116*(1+_xlfn.XLOOKUP("Digital Services",'01_Assumptions'!$A$4:$A$6,'01_Assumptions'!$B$4:$B$6)) -> 787968 | F116: ='02_Actual_Revenue'!E116*(1+_xlfn.XLOOKUP("Digital Services",'01_Assumptions'!$A$4:$A$6,'01_Assumptions'!$C$4:$C$6)) -> 15.3 | G116: =E116*F116 -> 12055910 | H116: =G116*'02_Actual_Revenue'!H116 -> 4219568.6 | I116: =G116-H116 -> 7836341.8 | J116: =I116/G116 -> 0.65
A117: ='02_Actual_Revenue'!A117 -> 45717 | B117: ='02_Actual_Revenue'!B117 -> P009 | C117: ='02_Actual_Revenue'!C117 -> R04 | D117: ='02_Actual_Revenue'!D117 -> 422400 | E117: =D117*(1+_xlfn.XLOOKUP("Digital Services",'01_Assumptions'!$A$4:$A$6,'01_Assumptions'!$B$4:$B$6)) -> 456192 | F117: ='02_Actual_Revenue'!E117*(1+_xlfn.XLOOKUP("Digital Services",'01_Assumptions'!$A$4:$A$6,'01_Assumptions'!$C$4:$C$6)) -> 15.3 | G117: =E117*F117 -> 6979737.6 | H117: =G117*'02_Actual_Revenue'!H117 -> 2442908.2 | I117: =G117-H117 -> 4536829.4 | J117: =I117/G117 -> 0.65
A118: ='02_Actual_Revenue'!A118 -> 45717 | B118: ='02_Actual_Revenue'!B118 -> P010 | C118: ='02_Actual_Revenue'!C118 -> R01 | D118: ='02_Actual_Revenue'!D118 -> 864000 | E118: =D118*(1+_xlfn.XLOOKUP("Digital Services",'01_Assumptions'!$A$4:$A$6,'01_Assumptions'!$B$4:$B$6)) -> 933120 | F118: ='02_Actual_Revenue'!E118*(1+_xlfn.XLOOKUP("Digital Services",'01_Assumptions'!$A$4:$A$6,'01_Assumptions'!$C$4:$C$6)) -> 8.16 | G118: =E118*F118 -> 7614259.2 | H118: =G118*'02_Actual_Revenue'!H118 -> 1142138.9 | I118: =G118-H118 -> 6472120.3 | J118: =I118/G118 -> 0.85
A119: ='02_Actual_Revenue'!A119 -> 45717 | B119: ='02_Actual_Revenue'!B119 -> P010 | C119: ='02_Actual_Revenue'!C119 -> R02 | D119: ='02_Actual_Revenue'!D119 -> 734400 | E119: =D119*(1+_xlfn.XLOOKUP("Digital Services",'01_Assumptions'!$A$4:$A$6,'01_Assumptions'!$B$4:$B$6)) -> 793152 | F119: ='02_Actual_Revenue'!E119*(1+_xlfn.XLOOKUP("Digital Services",'01_Assumptions'!$A$4:$A$6,'01_Assumptions'!$C$4:$C$6)) -> 8.16 | G119: =E119*F119 -> 6472120.3 | H119: =G119*'02_Actual_Revenue'!H119 -> 970818.05 | I119: =G119-H119 -> 5501302.3 | J119: =I119/G119 -> 0.85
A120: ='02_Actual_Revenue'!A120 -> 45717 | B120: ='02_Actual_Revenue'!B120 -> P010 | C120: ='02_Actual_Revenue'!C120 -> R03 | D120: ='02_Actual_Revenue'!D120 -> 820800 | E120: =D120*(1+_xlfn.XLOOKUP("Digital Services",'01_Assumptions'!$A$4:$A$6,'01_Assumptions'!$B$4:$B$6)) -> 886464 | F120: ='02_Actual_Revenue'!E120*(1+_xlfn.XLOOKUP("Digital Services",'01_Assumptions'!$A$4:$A$6,'01_Assumptions'!$C$4:$C$6)) -> 8.16 | G120: =E120*F120 -> 7233546.2 | H120: =G120*'02_Actual_Revenue'!H120 -> 1085031.9 | I120: =G120-H120 -> 6148514.3 | J120: =I120/G120 -> 0.85
A121: ='02_Actual_Revenue'!A121 -> 45717 | B121: ='02_Actual_Revenue'!B121 -> P010 | C121: ='02_Actual_Revenue'!C121 -> R04 | D121: ='02_Actual_Revenue'!D121 -> 475200 | E121: =D121*(1+_xlfn.XLOOKUP("Digital Services",'01_Assumptions'!$A$4:$A$6,'01_Assumptions'!$B$4:$B$6)) -> 513216 | F121: ='02_Actual_Revenue'!E121*(1+_xlfn.XLOOKUP("Digital Services",'01_Assumptions'!$A$4:$A$6,'01_Assumptions'!$C$4:$C$6)) -> 8.16 | G121: =E121*F121 -> 4187842.6 | H121: =G121*'02_Actual_Revenue'!H121 -> 628176.38 | I121: =G121-H121 -> 3559666.2 | J121: =I121/G121 -> 0.85
...

Sheet 06_Forecast
A1: Forecast P&L
A3: $M | B3: Budget | C3: YTD Actual | D3: Forecast Remaining | E3: FY Forecast | F3: Variance
A4: Revenue | B4: ='05_Budget'!B723 -> 3.7477708e+10 | C4: ='02_Actual_Revenue'!B723 -> 34530245600 | D4: =(B4-C4)*(C4/B4) -> 2.7156571e+09 | E4: =C4+D4 -> 3.7245903e+10 | F4: =E4-B4 -> -2.3180541e+08
A5: COGS | B5: ='05_Budget'!B724 -> 2.0421871e+10 | C5: ='02_Actual_Revenue'!B724 -> 1.8854969e+10 | D5: =(B5-C5)*(C5/B5) -> 1.4466789e+09 | E5: =C5+D5 -> 2.0301648e+10 | F5: =E5-B5 -> -1.2022317e+08
A6: Gross Profit | B6: ='05_Budget'!B725 -> 1.7055837e+10 | C6: ='02_Actual_Revenue'!B725 -> 1.5675277e+10 | D6: =D4-D5 -> 1.2689782e+09 | E6: =E4-E5 -> 1.6944255e+10 | F6: =F4-F5 -> -1.1158223e+08
A7: Gross Margin | B7: ='05_Budget'!B726 -> 0.45509285 | C7: ='02_Actual_Revenue'!B726 -> 0.45395787 | D7: =D6/D4 -> 0.46728219 | E7: =E6/E4 -> 0.45492937 | F7: =E7-B7 -> -0.0001634877
A8: Opex | B8: ='05_Budget'!B1308 -> 7624080000 | C8: ='03_Actual_Opex'!B579 -> 7128000000 | D8: =(B8-C8)*(C8/B8) -> 4.638013e+08 | E8: =C8+D8 -> 7.5918013e+09 | F8: =E8-B8 -> -32278697
A9: EBIT | B9: =B6-B8 -> 9.4317572e+09 | C9: =C6-C8 -> 8.5472768e+09 | D9: =D6-D8 -> 8.051769e+08 | E9: =E6-E8 -> 9.3524537e+09 | F9: =F6-F8 -> -79303534
A10: EBIT Margin | B10: =B9/B4 -> 0.25166313 | C10: =C9/C4 -> 0.24753015 | D10: =D9/D4 -> 0.29649432 | E10: =E9/E4 -> 0.2511002 | F10: =E10-B10 -> -0.0005629253

Sheet 07_PnL
A1: Budget P&L
A3: $M | B3: 2026 Budget
A4: Revenue | B4: ='05_Budget'!B723 -> 3.7477708e+10
A5: COGS | B5: ='05_Budget'!B724 -> 2.0421871e+10
A6: Gross Profit | B6: ='05_Budget'!B725 -> 1.7055837e+10
A7: Gross Margin | B7: ='05_Budget'!B726 -> 0.45509285
A8: Operating Expenses | B8: ='05_Budget'!B1308 -> 7624080000
A9: EBIT | B9: =B6-B8 -> 9.4317572e+09
A10: EBIT Margin | B10: =B9/B4 -> 0.25166313

Sheet 08_Variance
A1: Month | B1: Category | C1: Actual | D1: Budget | E1: Variance $ | F1: Variance % | G1: Status | H1: Materiality
A2: 45658 | B2: Revenue | C2: =SUM('02_Actual_Revenue'!F2:F41) -> 1774738880 | D2: =SUM('05_Budget'!G2:G41) -> 1.9262286e+09 | E2: =C2-D2 -> -1.5148969e+08 | F2: =IFERROR(E2/D2, 0) -> -0.078645752 | G2: =IF(OR(B2="COGS", B2="Operating Expenses"), IF(E2<=0, "Favorable", "Unfavorable"), IF(E2>=0, "Favorable", "Unfavorable")) -> Unfavorable | H2: =IF(OR(ABS(F2)>=0.05, ABS(E2)>=5000000), "Material", "Not Material") -> Material
A3: 45658 | B3: COGS | C3: =SUM('02_Actual_Revenue'!G2:G41) -> 9.690822e+08 | D3: =SUM('05_Budget'!H2:H41) -> 1.0496157e+09 | E3: =C3-D3 -> -80533515 | F3: =IFERROR(E3/D3, 0) -> -0.076726667 | G3: =IF(OR(B3="COGS", B3="Operating Expenses"), IF(E3<=0, "Favorable", "Unfavorable"), IF(E3>=0, "Favorable", "Unfavorable")) -> Favorable | H3: =IF(OR(ABS(F3)>=0.05, ABS(E3)>=5000000), "Material", "Not Material") -> Material
A4: 45658 | B4: Gross Profit | C4: =C2-C3 -> 8.0565668e+08 | D4: =D2-D3 -> 8.7661286e+08 | E4: =C4-D4 -> -70956179 | F4: =IFERROR(E4/D4, 0) -> -0.080943575 | G4: =IF(OR(B4="COGS", B4="Operating Expenses"), IF(E4<=0, "Favorable", "Unfavorable"), IF(E4>=0, "Favorable", "Unfavorable")) -> Unfavorable | H4: =IF(OR(ABS(F4)>=0.05, ABS(E4)>=5000000), "Material", "Not Material") -> Material
A5: 45658 | B5: Operating Expenses | C5: =SUM('03_Actual_Opex'!E2:E33) -> 396000000 | D5: =SUM('05_Budget'!F731:F762) -> 423560000 | E5: =C5-D5 -> -27560000 | F5: =IFERROR(E5/D5, 0) -> -0.065067523 | G5: =IF(OR(B5="COGS", B5="Operating Expenses"), IF(E5<=0, "Favorable", "Unfavorable"), IF(E5>=0, "Favorable", "Unfavorable")) -> Favorable | H5: =IF(OR(ABS(F5)>=0.05, ABS(E5)>=5000000), "Material", "Not Material") -> Material
A6: 45658 | B6: EBIT | C6: =C4-C5 -> 4.0965668e+08 | D6: =D4-D5 -> 4.5305286e+08 | E6: =C6-D6 -> -43396179 | F6: =IFERROR(E6/D6, 0) -> -0.095786127 | G6: =IF(OR(B6="COGS", B6="Operating Expenses"), IF(E6<=0, "Favorable", "Unfavorable"), IF(E6>=0, "Favorable", "Unfavorable")) -> Unfavorable | H6: =IF(OR(ABS(F6)>=0.05, ABS(E6)>=5000000), "Material", "Not Material") -> Material
A7: 45689 | B7: Revenue | C7: =SUM('02_Actual_Revenue'!F42:F81) -> 1736157600 | D7: =SUM('05_Budget'!G42:G81) -> 1.884354e+09 | E7: =C7-D7 -> -1.4819644e+08 | F7: =IFERROR(E7/D7, 0) -> -0.078645752 | G7: =IF(OR(B7="COGS", B7="Operating Expenses"), IF(E7<=0, "Favorable", "Unfavorable"), IF(E7>=0, "Favorable", "Unfavorable")) -> Unfavorable | H7: =IF(OR(ABS(F7)>=0.05, ABS(E7)>=5000000), "Material", "Not Material") -> Material
A8: 45689 | B8: COGS | C8: =SUM('02_Actual_Revenue'!G42:G81) -> 9.4801519e+08 | D8: =SUM('05_Budget'!H42:H81) -> 1.026798e+09 | E8: =C8-D8 -> -78782787 | F8: =IFERROR(E8/D8, 0) -> -0.076726667 | G8: =IF(OR(B8="COGS", B8="Operating Expenses"), IF(E8<=0, "Favorable", "Unfavorable"), IF(E8>=0, "Favorable", "Unfavorable")) -> Favorable | H8: =IF(OR(ABS(F8)>=0.05, ABS(E8)>=5000000), "Material", "Not Material") -> Material
A9: 45689 | B9: Gross Profit | C9: =C7-C8 -> 7.8814241e+08 | D9: =D7-D8 -> 8.5755606e+08 | E9: =C9-D9 -> -69413653 | F9: =IFERROR(E9/D9, 0) -> -0.080943575 | G9: =IF(OR(B9="COGS", B9="Operating Expenses"), IF(E9<=0, "Favorable", "Unfavorable"), IF(E9>=0, "Favorable", "Unfavorable")) -> Unfavorable | H9: =IF(OR(ABS(F9)>=0.05, ABS(E9)>=5000000), "Material", "Not Material") -> Material
A10: 45689 | B10: Operating Expenses | C10: =SUM('03_Actual_Opex'!E34:E65) -> 396000000 | D10: =SUM('05_Budget'!F763:F794) -> 423560000 | E10: =C10-D10 -> -27560000 | F10: =IFERROR(E10/D10, 0) -> -0.065067523 | G10: =IF(OR(B10="COGS", B10="Operating Expenses"), IF(E10<=0, "Favorable", "Unfavorable"), IF(E10>=0, "Favorable", "Unfavorable")) -> Favorable | H10: =IF(OR(ABS(F10)>=0.05, ABS(E10)>=5000000), "Material", "Not Material") -> Material
A11: 45689 | B11: EBIT | C11: =C9-C10 -> 3.9214241e+08 | D11: =D9-D10 -> 4.3399606e+08 | E11: =C11-D11 -> -41853653 | F11: =IFERROR(E11/D11, 0) -> -0.096437864 | G11: =IF(OR(B11="COGS", B11="Operating Expenses"), IF(E11<=0, "Favorable", "Unfavorable"), IF(E11>=0, "Favorable", "Unfavorable")) -> Unfavorable | H11: =IF(OR(ABS(F11)>=0.05, ABS(E11)>=5000000), "Material", "Not Material") -> Material
A12: 45717 | B12: Revenue | C12: =SUM('02_Actual_Revenue'!F82:F121) -> 1851901440 | D12: =SUM('05_Budget'!G82:G121) -> 2.0099776e+09 | E12: =C12-D12 -> -1.580762e+08 | F12: =IFERROR(E12/D12, 0) -> -0.078645752 | G12: =IF(OR(B12="COGS", B12="Operating Expenses"), IF(E12<=0, "Favorable", "Unfavorable"), IF(E12>=0, "Favorable", "Unfavorable")) -> Unfavorable | H12: =IF(OR(ABS(F12)>=0.05, ABS(E12)>=5000000), "Material", "Not Material") -> Material
A13: 45717 | B13: COGS | C13: =SUM('02_Actual_Revenue'!G82:G121) -> 1.0112162e+09 | D13: =SUM('05_Budget'!H82:H121) -> 1.0952512e+09 | E13: =C13-D13 -> -84034972 | F13: =IFERROR(E13/D13, 0) -> -0.076726667 | G13: =IF(OR(B13="COGS", B13="Operating Expenses"), IF(E13<=0, "Favorable", "Unfavorable"), IF(E13>=0, "Favorable", "Unfavorable")) -> Favorable | H13: =IF(OR(ABS(F13)>=0.05, ABS(E13)>=5000000), "Material", "Not Material") -> Material
A14: 45717 | B14: Gross Profit | C14: =C12-C13 -> 8.4068523e+08 | D14: =D12-D13 -> 9.1472646e+08 | E14: =C14-D14 -> -74041230 | F14: =IFERROR(E14/D14, 0) -> -0.080943575 | G14: =IF(OR(B14="COGS", B14="Operating Expenses"), IF(E14<=0, "Favorable", "Unfavorable"), IF(E14>=0, "Favorable", "Unfavorable")) -> Unfavorable | H14: =IF(OR(ABS(F14)>=0.05, ABS(E14)>=5000000), "Material", "Not Material") -> Material
A15: 45717 | B15: Operating Expenses | C15: =SUM('03_Actual_Opex'!E66:E97) -> 396000000 | D15: =SUM('05_Budget'!F795:F826) -> 423560000 | E15: =C15-D15 -> -27560000 | F15: =IFERROR(E15/D15, 0) -> -0.065067523 | G15: =IF(OR(B15="COGS", B15="Operating Expenses"), IF(E15<=0, "Favorable", "Unfavorable"), IF(E15>=0, "Favorable", "Unfavorable")) -> Favorable | H15: =IF(OR(ABS(F15)>=0.05, ABS(E15)>=5000000), "Material", "Not Material") -> Material
A16: 45717 | B16: EBIT | C16: =C14-C15 -> 4.4468523e+08 | D16: =D14-D15 -> 4.9116646e+08 | E16: =C16-D16 -> -46481230 | F16: =IFERROR(E16/D16, 0) -> -0.094634372 | G16: =IF(OR(B16="COGS", B16="Operating Expenses"), IF(E16<=0, "Favorable", "Unfavorable"), IF(E16>=0, "Favorable", "Unfavorable")) -> Unfavorable | H16: =IF(OR(ABS(F16)>=0.05, ABS(E16)>=5000000), "Material", "Not Material") -> Material
A17: 45748 | B17: Revenue | C17: =SUM('02_Actual_Revenue'!F122:F161) -> 1832610800 | D17: =SUM('05_Budget'!G122:G161) -> 1.9890404e+09 | E17: =C17-D17 -> -1.5642958e+08 | F17: =IFERROR(E17/D17, 0) -> -0.078645752 | G17: =IF(OR(B17="COGS", B17="Operating Expenses"), IF(E17<=0, "Favorable", "Unfavorable"), IF(E17>=0, "Favorable", "Unfavorable")) -> Unfavorable | H17: =IF(OR(ABS(F17)>=0.05, ABS(E17)>=5000000), "Material", "Not Material") -> Material
A18: 45748 | B18: COGS | C18: =SUM('02_Actual_Revenue'!G122:G161) -> 1.0006827e+09 | D18: =SUM('05_Budget'!H122:H161) -> 1.0838423e+09 | E18: =C18-D18 -> -83159608 | F18: =IFERROR(E18/D18, 0) -> -0.076726667 | G18: =IF(OR(B18="COGS", B18="Operating Expenses"), IF(E18<=0, "Favorable", "Unfavorable"), IF(E18>=0, "Favorable", "Unfavorable")) -> Favorable | H18: =IF(OR(ABS(F18)>=0.05, ABS(E18)>=5000000), "Material", "Not Material") -> Material
A19: 45748 | B19: Gross Profit | C19: =C17-C18 -> 8.319281e+08 | D19: =D17-D18 -> 9.0519806e+08 | E19: =C19-D19 -> -73269967 | F19: =IFERROR(E19/D19, 0) -> -0.080943575 | G19: =IF(OR(B19="COGS", B19="Operating Expenses"), IF(E19<=0, "Favorable", "Unfavorable"), IF(E19>=0, "Favorable", "Unfavorable")) -> Unfavorable | H19: =IF(OR(ABS(F19)>=0.05, ABS(E19)>=5000000), "Material", "Not Material") -> Material
A20: 45748 | B20: Operating Expenses | C20: =SUM('03_Actual_Opex'!E98:E129) -> 396000000 | D20: =SUM('05_Budget'!F827:F858) -> 423560000 | E20: =C20-D20 -> -27560000 | F20: =IFERROR(E20/D20, 0) -> -0.065067523 | G20: =IF(OR(B20="COGS", B20="Operating Expenses"), IF(E20<=0, "Favorable", "Unfavorable"), IF(E20>=0, "Favorable", "Unfavorable")) -> Favorable | H20: =IF(OR(ABS(F20)>=0.05, ABS(E20)>=5000000), "Material", "Not Material") -> Material
A21: 45748 | B21: EBIT | C21: =C19-C20 -> 4.359281e+08 | D21: =D19-D20 -> 4.8163806e+08 | E21: =C21-D21 -> -45709967 | F21: =IFERROR(E21/D21, 0) -> -0.094905222 | G21: =IF(OR(B21="COGS", B21="Operating Expenses"), IF(E21<=0, "Favorable", "Unfavorable"), IF(E21>=0, "Favorable", "Unfavorable")) -> Unfavorable | H21: =IF(OR(ABS(F21)>=0.05, ABS(E21)>=5000000), "Material", "Not Material") -> Material
A22: 45778 | B22: Revenue | C22: =SUM('02_Actual_Revenue'!F162:F201) -> 1929064000 | D22: =SUM('05_Budget'!G162:G201) -> 2.0937267e+09 | E22: =C22-D22 -> -1.6466271e+08 | F22: =IFERROR(E22/D22, 0) -> -0.078645752 | G22: =IF(OR(B22="COGS", B22="Operating Expenses"), IF(E22<=0, "Favorable", "Unfavorable"), IF(E22>=0, "Favorable", "Unfavorable")) -> Unfavorable | H22: =IF(OR(ABS(F22)>=0.05, ABS(E22)>=5000000), "Material", "Not Material") -> Material
A23: 45778 | B23: COGS | C23: =SUM('02_Actual_Revenue'!G162:G201) -> 1053350215 | D23: =SUM('05_Budget'!H162:H201) -> 1.1408866e+09 | E23: =C23-D23 -> -87536430 | F23: =IFERROR(E23/D23, 0) -> -0.076726667 | G23: =IF(OR(B23="COGS", B23="Operating Expenses"), IF(E23<=0, "Favorable", "Unfavorable"), IF(E23>=0, "Favorable", "Unfavorable")) -> Favorable | H23: =IF(OR(ABS(F23)>=0.05, ABS(E23)>=5000000), "Material", "Not Material") -> Material
A24: 45778 | B24: Gross Profit | C24: =C22-C23 -> 875713785 | D24: =D22-D23 -> 9.5284007e+08 | E24: =C24-D24 -> -77126281 | F24: =IFERROR(E24/D24, 0) -> -0.080943575 | G24: =IF(OR(B24="COGS", B24="Operating Expenses"), IF(E24<=0, "Favorable", "Unfavorable"), IF(E24>=0, "Favorable", "Unfavorable")) -> Unfavorable | H24: =IF(OR(ABS(F24)>=0.05, ABS(E24)>=5000000), "Material", "Not Material") -> Material
A25: 45778 | B25: Operating Expenses | C25: =SUM('03_Actual_Opex'!E130:E161) -> 396000000 | D25: =SUM('05_Budget'!F859:F890) -> 423560000 | E25: =C25-D25 -> -27560000 | F25: =IFERROR(E25/D25, 0) -> -0.065067523 | G25: =IF(OR(B25="COGS", B25="Operating Expenses"), IF(E25<=0, "Favorable", "Unfavorable"), IF(E25>=0, "Favorable", "Unfavorable")) -> Favorable | H25: =IF(OR(ABS(F25)>=0.05, ABS(E25)>=5000000), "Material", "Not Material") -> Material
A26: 45778 | B26: EBIT | C26: =C24-C25 -> 479713785 | D26: =D24-D25 -> 5.2928007e+08 | E26: =C26-D26 -> -49566281 | F26: =IFERROR(E26/D26, 0) -> -0.093648494 | G26: =IF(OR(B26="COGS", B26="Operating Expenses"), IF(E26<=0, "Favorable", "Unfavorable"), IF(E26>=0, "Favorable", "Unfavorable")) -> Unfavorable | H26: =IF(OR(ABS(F26)>=0.05, ABS(E26)>=5000000), "Material", "Not Material") -> Material
A27: 45809 | B27: Revenue | C27: =SUM('02_Actual_Revenue'!F202:F241) -> 1967645280 | D27: =SUM('05_Budget'!G202:G241) -> 2.1356012e+09 | E27: =C27-D27 -> -1.6795597e+08 | F27: =IFERROR(E27/D27, 0) -> -0.078645752 | G27: =IF(OR(B27="COGS", B27="Operating Expenses"), IF(E27<=0, "Favorable", "Unfavorable"), IF(E27>=0, "Favorable", "Unfavorable")) -> Unfavorable | H27: =IF(OR(ABS(F27)>=0.05, ABS(E27)>=5000000), "Material", "Not Material") -> Material
A28: 45809 | B28: COGS | C28: =SUM('02_Actual_Revenue'!G202:G241) -> 1.0744172e+09 | D28: =SUM('05_Budget'!H202:H241) -> 1.1637044e+09 | E28: =C28-D28 -> -89287158 | F28: =IFERROR(E28/D28, 0) -> -0.076726667 | G28: =IF(OR(B28="COGS", B28="Operating Expenses"), IF(E28<=0, "Favorable", "Unfavorable"), IF(E28>=0, "Favorable", "Unfavorable")) -> Favorable | H28: =IF(OR(ABS(F28)>=0.05, ABS(E28)>=5000000), "Material", "Not Material") -> Material
A29: 45809 | B29: Gross Profit | C29: =C27-C28 -> 8.9322806e+08 | D29: =D27-D28 -> 9.7189687e+08 | E29: =C29-D29 -> -78668807 | F29: =IFERROR(E29/D29, 0) -> -0.080943575 | G29: =IF(OR(B29="COGS", B29="Operating Expenses"), IF(E29<=0, "Favorable", "Unfavorable"), IF(E29>=0, "Favorable", "Unfavorable")) -> Unfavorable | H29: =IF(OR(ABS(F29)>=0.05, ABS(E29)>=5000000), "Material", "Not Material") -> Material
A30: 45809 | B30: Operating Expenses | C30: =SUM('03_Actual_Opex'!E162:E193) -> 396000000 | D30: =SUM('05_Budget'!F891:F922) -> 423560000 | E30: =C30-D30 -> -27560000 | F30: =IFERROR(E30/D30, 0) -> -0.065067523 | G30: =IF(OR(B30="COGS", B30="Operating Expenses"), IF(E30<=0, "Favorable", "Unfavorable"), IF(E30>=0, "Favorable", "Unfavorable")) -> Favorable | H30: =IF(OR(ABS(F30)>=0.05, ABS(E30)>=5000000), "Material", "Not Material") -> Material
A31: 45809 | B31: EBIT | C31: =C29-C30 -> 4.9722806e+08 | D31: =D29-D30 -> 5.4833687e+08 | E31: =C31-D31 -> -51108807 | F31: =IFERROR(E31/D31, 0) -> -0.09320695 | G31: =IF(OR(B31="COGS", B31="Operating Expenses"), IF(E31<=0, "Favorable", "Unfavorable"), IF(E31>=0, "Favorable", "Unfavorable")) -> Unfavorable | H31: =IF(OR(ABS(F31)>=0.05, ABS(E31)>=5000000), "Material", "Not Material") -> Material
A32: 45839 | B32: Revenue | C32: =SUM('02_Actual_Revenue'!F242:F281) -> 1986935920 | D32: =SUM('05_Budget'!G242:G281) -> 2.1565385e+09 | E32: =C32-D32 -> -1.6960259e+08 | F32: =IFERROR(E32/D32, 0) -> -0.078645752 | G32: =IF(OR(B32="COGS", B32="Operating Expenses"), IF(E32<=0, "Favorable", "Unfavorable"), IF(E32>=0, "Favorable", "Unfavorable")) -> Unfavorable | H32: =IF(OR(ABS(F32)>=0.05, ABS(E32)>=5000000), "Material", "Not Material") -> Material
A33: 45839 | B33: COGS | C33: =SUM('02_Actual_Revenue'!G242:G281) -> 1.0849507e+09 | D33: =SUM('05_Budget'!H242:H281) -> 1.1751132e+09 | E33: =C33-D33 -> -90162522 | F33: =IFERROR(E33/D33, 0) -> -0.076726667 | G33: =IF(OR(B33="COGS", B33="Operating Expenses"), IF(E33<=0, "Favorable", "Unfavorable"), IF(E33>=0, "Favorable", "Unfavorable")) -> Favorable | H33: =IF(OR(ABS(F33)>=0.05, ABS(E33)>=5000000), "Material", "Not Material") -> Material
A34: 45839 | B34: Gross Profit | C34: =C32-C33 -> 9.019852e+08 | D34: =D32-D33 -> 9.8142527e+08 | E34: =C34-D34 -> -79440070 | F34: =IFERROR(E34/D34, 0) -> -0.080943575 | G34: =IF(OR(B34="COGS", B34="Operating Expenses"), IF(E34<=0, "Favorable", "Unfavorable"), IF(E34>=0, "Favorable", "Unfavorable")) -> Unfavorable | H34: =IF(OR(ABS(F34)>=0.05, ABS(E34)>=5000000), "Material", "Not Material") -> Material
A35: 45839 | B35: Operating Expenses | C35: =SUM('03_Actual_Opex'!E194:E225) -> 396000000 | D35: =SUM('05_Budget'!F923:F954) -> 423560000 | E35: =C35-D35 -> -27560000 | F35: =IFERROR(E35/D35, 0) -> -0.065067523 | G35: =IF(OR(B35="COGS", B35="Operating Expenses"), IF(E35<=0, "Favorable", "Unfavorable"), IF(E35>=0, "Favorable", "Unfavorable")) -> Favorable | H35: =IF(OR(ABS(F35)>=0.05, ABS(E35)>=5000000), "Material", "Not Material") -> Material
A36: 45839 | B36: EBIT | C36: =C34-C35 -> 5.059852e+08 | D36: =D34-D35 -> 5.5786527e+08 | E36: =C36-D36 -> -51880070 | F36: =IFERROR(E36/D36, 0) -> -0.09299749 | G36: =IF(OR(B36="COGS", B36="Operating Expenses"), IF(E36<=0, "Favorable", "Unfavorable"), IF(E36>=0, "Favorable", "Unfavorable")) -> Unfavorable | H36: =IF(OR(ABS(F36)>=0.05, ABS(E36)>=5000000), "Material", "Not Material") -> Material
A37: 45870 | B37: Revenue | C37: =SUM('02_Actual_Revenue'!F282:F321) -> 1967645280 | D37: =SUM('05_Budget'!G282:G321) -> 2.1356012e+09 | E37: =C37-D37 -> -1.6795597e+08 | F37: =IFERROR(E37/D37, 0) -> -0.078645752 | G37: =IF(OR(B37="COGS", B37="Operating Expenses"), IF(E37<=0, "Favorable", "Unfavorable"), IF(E37>=0, "Favorable", "Unfavorable")) -> Unfavorable | H37: =IF(OR(ABS(F37)>=0.05, ABS(E37)>=5000000), "Material", "Not Material") -> Material
A38: 45870 | B38: COGS | C38: =SUM('02_Actual_Revenue'!G282:G321) -> 1.0744172e+09 | D38: =SUM('05_Budget'!H282:H321) -> 1.1637044e+09 | E38: =C38-D38 -> -89287158 | F38: =IFERROR(E38/D38, 0) -> -0.076726667 | G38: =IF(OR(B38="COGS", B38="Operating Expenses"), IF(E38<=0, "Favorable", "Unfavorable"), IF(E38>=0, "Favorable", "Unfavorable")) -> Favorable | H38: =IF(OR(ABS(F38)>=0.05, ABS(E38)>=5000000), "Material", "Not Material") -> Material
A39: 45870 | B39: Gross Profit | C39: =C37-C38 -> 8.9322806e+08 | D39: =D37-D38 -> 9.7189687e+08 | E39: =C39-D39 -> -78668807 | F39: =IFERROR(E39/D39, 0) -> -0.080943575 | G39: =IF(OR(B39="COGS", B39="Operating Expenses"), IF(E39<=0, "Favorable", "Unfavorable"), IF(E39>=0, "Favorable", "Unfavorable")) -> Unfavorable | H39: =IF(OR(ABS(F39)>=0.05, ABS(E39)>=5000000), "Material", "Not Material") -> Material
A40: 45870 | B40: Operating Expenses | C40: =SUM('03_Actual_Opex'!E226:E257) -> 396000000 | D40: =SUM('05_Budget'!F955:F986) -> 423560000 | E40: =C40-D40 -> -27560000 | F40: =IFERROR(E40/D40, 0) -> -0.065067523 | G40: =IF(OR(B40="COGS", B40="Operating Expenses"), IF(E40<=0, "Favorable", "Unfavorable"), IF(E40>=0, "Favorable", "Unfavorable")) -> Favorable | H40: =IF(OR(ABS(F40)>=0.05, ABS(E40)>=5000000), "Material", "Not Material") -> Material
A41: 45870 | B41: EBIT | C41: =C39-C40 -> 4.9722806e+08 | D41: =D39-D40 -> 5.4833687e+08 | E41: =C41-D41 -> -51108807 | F41: =IFERROR(E41/D41, 0) -> -0.09320695 | G41: =IF(OR(B41="COGS", B41="Operating Expenses"), IF(E41<=0, "Favorable", "Unfavorable"), IF(E41>=0, "Favorable", "Unfavorable")) -> Unfavorable | H41: =IF(OR(ABS(F41)>=0.05, ABS(E41)>=5000000), "Material", "Not Material") -> Material
A42: 45901 | B42: Revenue | C42: =SUM('02_Actual_Revenue'!F322:F361) -> 1929064000 | D42: =SUM('05_Budget'!G322:G361) -> 2.0937267e+09 | E42: =C42-D42 -> -1.6466271e+08 | F42: =IFERROR(E42/D42, 0) -> -0.078645752 | G42: =IF(OR(B42="COGS", B42="Operating Expenses"), IF(E42<=0, "Favorable", "Unfavorable"), IF(E42>=0, "Favorable", "Unfavorable")) -> Unfavorable | H42: =IF(OR(ABS(F42)>=0.05, ABS(E42)>=5000000), "Material", "Not Material") -> Material
A43: 45901 | B43: COGS | C43: =SUM('02_Actual_Revenue'!G322:G361) -> 1053350215 | D43: =SUM('05_Budget'!H322:H361) -> 1.1408866e+09 | E43: =C43-D43 -> -87536430 | F43: =IFERROR(E43/D43, 0) -> -0.076726667 | G43: =IF(OR(B43="COGS", B43="Operating Expenses"), IF(E43<=0, "Favorable", "Unfavorable"), IF(E43>=0, "Favorable", "Unfavorable")) -> Favorable | H43: =IF(OR(ABS(F43)>=0.05, ABS(E43)>=5000000), "Material", "Not Material") -> Material
A44: 45901 | B44: Gross Profit | C44: =C42-C43 -> 875713785 | D44: =D42-D43 -> 9.5284007e+08 | E44: =C44-D44 -> -77126281 | F44: =IFERROR(E44/D44, 0) -> -0.080943575 | G44: =IF(OR(B44="COGS", B44="Operating Expenses"), IF(E44<=0, "Favorable", "Unfavorable"), IF(E44>=0, "Favorable", "Unfavorable")) -> Unfavorable | H44: =IF(OR(ABS(F44)>=0.05, ABS(E44)>=5000000), "Material", "Not Material") -> Material
A45: 45901 | B45: Operating Expenses | C45: =SUM('03_Actual_Opex'!E258:E289) -> 396000000 | D45: =SUM('05_Budget'!F987:F1018) -> 423560000 | E45: =C45-D45 -> -27560000 | F45: =IFERROR(E45/D45, 0) -> -0.065067523 | G45: =IF(OR(B45="COGS", B45="Operating Expenses"), IF(E45<=0, "Favorable", "Unfavorable"), IF(E45>=0, "Favorable", "Unfavorable")) -> Favorable | H45: =IF(OR(ABS(F45)>=0.05, ABS(E45)>=5000000), "Material", "Not Material") -> Material
A46: 45901 | B46: EBIT | C46: =C44-C45 -> 479713785 | D46: =D44-D45 -> 5.2928007e+08 | E46: =C46-D46 -> -49566281 | F46: =IFERROR(E46/D46, 0) -> -0.093648494 | G46: =IF(OR(B46="COGS", B46="Operating Expenses"), IF(E46<=0, "Favorable", "Unfavorable"), IF(E46>=0, "Favorable", "Unfavorable")) -> Unfavorable | H46: =IF(OR(ABS(F46)>=0.05, ABS(E46)>=5000000), "Material", "Not Material") -> Material
A47: 45931 | B47: Revenue | C47: =SUM('02_Actual_Revenue'!F362:F401) -> 2025517200 | D47: =SUM('05_Budget'!G362:G401) -> 2.198413e+09 | E47: =C47-D47 -> -1.7289585e+08 | F47: =IFERROR(E47/D47, 0) -> -0.078645752 | G47: =IF(OR(B47="COGS", B47="Operating Expenses"), IF(E47<=0, "Favorable", "Unfavorable"), IF(E47>=0, "Favorable", "Unfavorable")) -> Unfavorable | H47: =IF(OR(ABS(F47)>=0.05, ABS(E47)>=5000000), "Material", "Not Material") -> Material
A48: 45931 | B48: COGS | C48: =SUM('02_Actual_Revenue'!G362:G401) -> 1.1060177e+09 | D48: =SUM('05_Budget'!H362:H401) -> 1.197931e+09 | E48: =C48-D48 -> -91913251 | F48: =IFERROR(E48/D48, 0) -> -0.076726667 | G48: =IF(OR(B48="COGS", B48="Operating Expenses"), IF(E48<=0, "Favorable", "Unfavorable"), IF(E48>=0, "Favorable", "Unfavorable")) -> Favorable | H48: =IF(OR(ABS(F48)>=0.05, ABS(E48)>=5000000), "Material", "Not Material") -> Material
A49: 45931 | B49: Gross Profit | C49: =C47-C48 -> 9.1949947e+08 | D49: =D47-D48 -> 1.0004821e+09 | E49: =C49-D49 -> -80982595 | F49: =IFERROR(E49/D49, 0) -> -0.080943575 | G49: =IF(OR(B49="COGS", B49="Operating Expenses"), IF(E49<=0, "Favorable", "Unfavorable"), IF(E49>=0, "Favorable", "Unfavorable")) -> Unfavorable | H49: =IF(OR(ABS(F49)>=0.05, ABS(E49)>=5000000), "Material", "Not Material") -> Material
A50: 45931 | B50: Operating Expenses | C50: =SUM('03_Actual_Opex'!E290:E321) -> 396000000 | D50: =SUM('05_Budget'!F1019:F1050) -> 423560000 | E50: =C50-D50 -> -27560000 | F50: =IFERROR(E50/D50, 0) -> -0.065067523 | G50: =IF(OR(B50="COGS", B50="Operating Expenses"), IF(E50<=0, "Favorable", "Unfavorable"), IF(E50>=0, "Favorable", "Unfavorable")) -> Favorable | H50: =IF(OR(ABS(F50)>=0.05, ABS(E50)>=5000000), "Material", "Not Material") -> Material
A51: 45931 | B51: EBIT | C51: =C49-C50 -> 5.2349947e+08 | D51: =D49-D50 -> 5.7692207e+08 | E51: =C51-D51 -> -53422595 | F51: =IFERROR(E51/D51, 0) -> -0.092599327 | G51: =IF(OR(B51="COGS", B51="Operating Expenses"), IF(E51<=0, "Favorable", "Unfavorable"), IF(E51>=0, "Favorable", "Unfavorable")) -> Unfavorable | H51: =IF(OR(ABS(F51)>=0.05, ABS(E51)>=5000000), "Material", "Not Material") -> Material
A52: 45962 | B52: Revenue | C52: =SUM('02_Actual_Revenue'!F402:F441) -> 2160551680 | D52: =SUM('05_Budget'!G402:G441) -> 2.3449739e+09 | E52: =C52-D52 -> -1.8442224e+08 | F52: =IFERROR(E52/D52, 0) -> -0.078645752 | G52: =IF(OR(B52="COGS", B52="Operating Expenses"), IF(E52<=0, "Favorable", "Unfavorable"), IF(E52>=0, "Favorable", "Unfavorable")) -> Unfavorable | H52: =IF(OR(ABS(F52)>=0.05, ABS(E52)>=5000000), "Material", "Not Material") -> Material
A53: 45962 | B53: COGS | C53: =SUM('02_Actual_Revenue'!G402:G441) -> 1.1797522e+09 | D53: =SUM('05_Budget'!H402:H441) -> 1.277793e+09 | E53: =C53-D53 -> -98040801 | F53: =IFERROR(E53/D53, 0) -> -0.076726667 | G53: =IF(OR(B53="COGS", B53="Operating Expenses"), IF(E53<=0, "Favorable", "Unfavorable"), IF(E53>=0, "Favorable", "Unfavorable")) -> Favorable | H53: =IF(OR(ABS(F53)>=0.05, ABS(E53)>=5000000), "Material", "Not Material") -> Material
A54: 45962 | B54: Gross Profit | C54: =C52-C53 -> 9.8079944e+08 | D54: =D52-D53 -> 1.0671809e+09 | E54: =C54-D54 -> -86381435 | F54: =IFERROR(E54/D54, 0) -> -0.080943575 | G54: =IF(OR(B54="COGS", B54="Operating Expenses"), IF(E54<=0, "Favorable", "Unfavorable"), IF(E54>=0, "Favorable", "Unfavorable")) -> Unfavorable | H54: =IF(OR(ABS(F54)>=0.05, ABS(E54)>=5000000), "Material", "Not Material") -> Material
A55: 45962 | B55: Operating Expenses | C55: =SUM('03_Actual_Opex'!E322:E353) -> 396000000 | D55: =SUM('05_Budget'!F1051:F1082) -> 423560000 | E55: =C55-D55 -> -27560000 | F55: =IFERROR(E55/D55, 0) -> -0.065067523 | G55: =IF(OR(B55="COGS", B55="Operating Expenses"), IF(E55<=0, "Favorable", "Unfavorable"), IF(E55>=0, "Favorable", "Unfavorable")) -> Favorable | H55: =IF(OR(ABS(F55)>=0.05, ABS(E55)>=5000000), "Material", "Not Material") -> Material
A56: 45962 | B56: EBIT | C56: =C54-C55 -> 5.8479944e+08 | D56: =D54-D55 -> 6.4362087e+08 | E56: =C56-D56 -> -58821435 | F56: =IFERROR(E56/D56, 0) -> -0.091391435 | G56: =IF(OR(B56="COGS", B56="Operating Expenses"), IF(E56<=0, "Favorable", "Unfavorable"), IF(E56>=0, "Favorable", "Unfavorable")) -> Unfavorable | H56: =IF(OR(ABS(F56)>=0.05, ABS(E56)>=5000000), "Material", "Not Material") -> Material
A57: 45992 | B57: Revenue | C57: =SUM('02_Actual_Revenue'!F442:F481) -> 2276295520 | D57: =SUM('05_Budget'!G442:G481) -> 2.4705975e+09 | E57: =C57-D57 -> -1.94302e+08 | F57: =IFERROR(E57/D57, 0) -> -0.078645752 | G57: =IF(OR(B57="COGS", B57="Operating Expenses"), IF(E57<=0, "Favorable", "Unfavorable"), IF(E57>=0, "Favorable", "Unfavorable")) -> Unfavorable | H57: =IF(OR(ABS(F57)>=0.05, ABS(E57)>=5000000), "Material", "Not Material") -> Material
A58: 45992 | B58: COGS | C58: =SUM('02_Actual_Revenue'!G442:G481) -> 1.2429533e+09 | D58: =SUM('05_Budget'!H442:H481) -> 1.3462462e+09 | E58: =C58-D58 -> -1.0329299e+08 | F58: =IFERROR(E58/D58, 0) -> -0.076726667 | G58: =IF(OR(B58="COGS", B58="Operating Expenses"), IF(E58<=0, "Favorable", "Unfavorable"), IF(E58>=0, "Favorable", "Unfavorable")) -> Favorable | H58: =IF(OR(ABS(F58)>=0.05, ABS(E58)>=5000000), "Material", "Not Material") -> Material
A59: 45992 | B59: Gross Profit | C59: =C57-C58 -> 1.0333423e+09 | D59: =D57-D58 -> 1.1243513e+09 | E59: =C59-D59 -> -91009012 | F59: =IFERROR(E59/D59, 0) -> -0.080943575 | G59: =IF(OR(B59="COGS", B59="Operating Expenses"), IF(E59<=0, "Favorable", "Unfavorable"), IF(E59>=0, "Favorable", "Unfavorable")) -> Unfavorable | H59: =IF(OR(ABS(F59)>=0.05, ABS(E59)>=5000000), "Material", "Not Material") -> Material
A60: 45992 | B60: Operating Expenses | C60: =SUM('03_Actual_Opex'!E354:E385) -> 396000000 | D60: =SUM('05_Budget'!F1083:F1114) -> 423560000 | E60: =C60-D60 -> -27560000 | F60: =IFERROR(E60/D60, 0) -> -0.065067523 | G60: =IF(OR(B60="COGS", B60="Operating Expenses"), IF(E60<=0, "Favorable", "Unfavorable"), IF(E60>=0, "Favorable", "Unfavorable")) -> Favorable | H60: =IF(OR(ABS(F60)>=0.05, ABS(E60)>=5000000), "Material", "Not Material") -> Material
A61: 45992 | B61: EBIT | C61: =C59-C60 -> 6.3734227e+08 | D61: =D59-D60 -> 7.0079128e+08 | E61: =C61-D61 -> -63449012 | F61: =IFERROR(E61/D61, 0) -> -0.0905391 | G61: =IF(OR(B61="COGS", B61="Operating Expenses"), IF(E61<=0, "Favorable", "Unfavorable"), IF(E61>=0, "Favorable", "Unfavorable")) -> Unfavorable | H61: =IF(OR(ABS(F61)>=0.05, ABS(E61)>=5000000), "Material", "Not Material") -> Material
A62: 46023 | B62: Revenue | C62: =SUM('02_Actual_Revenue'!F482:F521) -> 1774738880 | D62: =SUM('05_Budget'!G482:G521) -> 1.9262286e+09 | E62: =C62-D62 -> -1.5148969e+08 | F62: =IFERROR(E62/D62, 0) -> -0.078645752 | G62: =IF(OR(B62="COGS", B62="Operating Expenses"), IF(E62<=0, "Favorable", "Unfavorable"), IF(E62>=0, "Favorable", "Unfavorable")) -> Unfavorable | H62: =IF(OR(ABS(F62)>=0.05, ABS(E62)>=5000000), "Material", "Not Material") -> Material
A63: 46023 | B63: COGS | C63: =SUM('02_Actual_Revenue'!G482:G521) -> 9.690822e+08 | D63: =SUM('05_Budget'!H482:H521) -> 1.0496157e+09 | E63: =C63-D63 -> -80533515 | F63: =IFERROR(E63/D63, 0) -> -0.076726667 | G63: =IF(OR(B63="COGS", B63="Operating Expenses"), IF(E63<=0, "Favorable", "Unfavorable"), IF(E63>=0, "Favorable", "Unfavorable")) -> Favorable | H63: =IF(OR(ABS(F63)>=0.05, ABS(E63)>=5000000), "Material", "Not Material") -> Material
A64: 46023 | B64: Gross Profit | C64: =C62-C63 -> 8.0565668e+08 | D64: =D62-D63 -> 8.7661286e+08 | E64: =C64-D64 -> -70956179 | F64: =IFERROR(E64/D64, 0) -> -0.080943575 | G64: =IF(OR(B64="COGS", B64="Operating Expenses"), IF(E64<=0, "Favorable", "Unfavorable"), IF(E64>=0, "Favorable", "Unfavorable")) -> Unfavorable | H64: =IF(OR(ABS(F64)>=0.05, ABS(E64)>=5000000), "Material", "Not Material") -> Material
A65: 46023 | B65: Operating Expenses | C65: =SUM('03_Actual_Opex'!E386:E417) -> 396000000 | D65: =SUM('05_Budget'!F1115:F1146) -> 423560000 | E65: =C65-D65 -> -27560000 | F65: =IFERROR(E65/D65, 0) -> -0.065067523 | G65: =IF(OR(B65="COGS", B65="Operating Expenses"), IF(E65<=0, "Favorable", "Unfavorable"), IF(E65>=0, "Favorable", "Unfavorable")) -> Favorable | H65: =IF(OR(ABS(F65)>=0.05, ABS(E65)>=5000000), "Material", "Not Material") -> Material
A66: 46023 | B66: EBIT | C66: =C64-C65 -> 4.0965668e+08 | D66: =D64-D65 -> 4.5305286e+08 | E66: =C66-D66 -> -43396179 | F66: =IFERROR(E66/D66, 0) -> -0.095786127 | G66: =IF(OR(B66="COGS", B66="Operating Expenses"), IF(E66<=0, "Favorable", "Unfavorable"), IF(E66>=0, "Favorable", "Unfavorable")) -> Unfavorable | H66: =IF(OR(ABS(F66)>=0.05, ABS(E66)>=5000000), "Material", "Not Material") -> Material
A67: 46054 | B67: Revenue | C67: =SUM('02_Actual_Revenue'!F522:F561) -> 1736157600 | D67: =SUM('05_Budget'!G522:G561) -> 1.884354e+09 | E67: =C67-D67 -> -1.4819644e+08 | F67: =IFERROR(E67/D67, 0) -> -0.078645752 | G67: =IF(OR(B67="COGS", B67="Operating Expenses"), IF(E67<=0, "Favorable", "Unfavorable"), IF(E67>=0, "Favorable", "Unfavorable")) -> Unfavorable | H67: =IF(OR(ABS(F67)>=0.05, ABS(E67)>=5000000), "Material", "Not Material") -> Material
A68: 46054 | B68: COGS | C68: =SUM('02_Actual_Revenue'!G522:G561) -> 9.4801519e+08 | D68: =SUM('05_Budget'!H522:H561) -> 1.026798e+09 | E68: =C68-D68 -> -78782787 | F68: =IFERROR(E68/D68, 0) -> -0.076726667 | G68: =IF(OR(B68="COGS", B68="Operating Expenses"), IF(E68<=0, "Favorable", "Unfavorable"), IF(E68>=0, "Favorable", "Unfavorable")) -> Favorable | H68: =IF(OR(ABS(F68)>=0.05, ABS(E68)>=5000000), "Material", "Not Material") -> Material
A69: 46054 | B69: Gross Profit | C69: =C67-C68 -> 7.8814241e+08 | D69: =D67-D68 -> 8.5755606e+08 | E69: =C69-D69 -> -69413653 | F69: =IFERROR(E69/D69, 0) -> -0.080943575 | G69: =IF(OR(B69="COGS", B69="Operating Expenses"), IF(E69<=0, "Favorable", "Unfavorable"), IF(E69>=0, "Favorable", "Unfavorable")) -> Unfavorable | H69: =IF(OR(ABS(F69)>=0.05, ABS(E69)>=5000000), "Material", "Not Material") -> Material
A70: 46054 | B70: Operating Expenses | C70: =SUM('03_Actual_Opex'!E418:E449) -> 396000000 | D70: =SUM('05_Budget'!F1147:F1178) -> 423560000 | E70: =C70-D70 -> -27560000 | F70: =IFERROR(E70/D70, 0) -> -0.065067523 | G70: =IF(OR(B70="COGS", B70="Operating Expenses"), IF(E70<=0, "Favorable", "Unfavorable"), IF(E70>=0, "Favorable", "Unfavorable")) -> Favorable | H70: =IF(OR(ABS(F70)>=0.05, ABS(E70)>=5000000), "Material", "Not Material") -> Material
A71: 46054 | B71: EBIT | C71: =C69-C70 -> 3.9214241e+08 | D71: =D69-D70 -> 4.3399606e+08 | E71: =C71-D71 -> -41853653 | F71: =IFERROR(E71/D71, 0) -> -0.096437864 | G71: =IF(OR(B71="COGS", B71="Operating Expenses"), IF(E71<=0, "Favorable", "Unfavorable"), IF(E71>=0, "Favorable", "Unfavorable")) -> Unfavorable | H71: =IF(OR(ABS(F71)>=0.05, ABS(E71)>=5000000), "Material", "Not Material") -> Material
A72: 46082 | B72: Revenue | C72: =SUM('02_Actual_Revenue'!F562:F601) -> 1851901440 | D72: =SUM('05_Budget'!G562:G601) -> 2.0099776e+09 | E72: =C72-D72 -> -1.580762e+08 | F72: =IFERROR(E72/D72, 0) -> -0.078645752 | G72: =IF(OR(B72="COGS", B72="Operating Expenses"), IF(E72<=0, "Favorable", "Unfavorable"), IF(E72>=0, "Favorable", "Unfavorable")) -> Unfavorable | H72: =IF(OR(ABS(F72)>=0.05, ABS(E72)>=5000000), "Material", "Not Material") -> Material
A73: 46082 | B73: COGS | C73: =SUM('02_Actual_Revenue'!G562:G601) -> 1.0112162e+09 | D73: =SUM('05_Budget'!H562:H601) -> 1.0952512e+09 | E73: =C73-D73 -> -84034972 | F73: =IFERROR(E73/D73, 0) -> -0.076726667 | G73: =IF(OR(B73="COGS", B73="Operating Expenses"), IF(E73<=0, "Favorable", "Unfavorable"), IF(E73>=0, "Favorable", "Unfavorable")) -> Favorable | H73: =IF(OR(ABS(F73)>=0.05, ABS(E73)>=5000000), "Material", "Not Material") -> Material
A74: 46082 | B74: Gross Profit | C74: =C72-C73 -> 8.4068523e+08 | D74: =D72-D73 -> 9.1472646e+08 | E74: =C74-D74 -> -74041230 | F74: =IFERROR(E74/D74, 0) -> -0.080943575 | G74: =IF(OR(B74="COGS", B74="Operating Expenses"), IF(E74<=0, "Favorable", "Unfavorable"), IF(E74>=0, "Favorable", "Unfavorable")) -> Unfavorable | H74: =IF(OR(ABS(F74)>=0.05, ABS(E74)>=5000000), "Material", "Not Material") -> Material
A75: 46082 | B75: Operating Expenses | C75: =SUM('03_Actual_Opex'!E450:E481) -> 396000000 | D75: =SUM('05_Budget'!F1179:F1210) -> 423560000 | E75: =C75-D75 -> -27560000 | F75: =IFERROR(E75/D75, 0) -> -0.065067523 | G75: =IF(OR(B75="COGS", B75="Operating Expenses"), IF(E75<=0, "Favorable", "Unfavorable"), IF(E75>=0, "Favorable", "Unfavorable")) -> Favorable | H75: =IF(OR(ABS(F75)>=0.05, ABS(E75)>=5000000), "Material", "Not Material") -> Material
A76: 46082 | B76: EBIT | C76: =C74-C75 -> 4.4468523e+08 | D76: =D74-D75 -> 4.9116646e+08 | E76: =C76-D76 -> -46481230 | F76: =IFERROR(E76/D76, 0) -> -0.094634372 | G76: =IF(OR(B76="COGS", B76="Operating Expenses"), IF(E76<=0, "Favorable", "Unfavorable"), IF(E76>=0, "Favorable", "Unfavorable")) -> Unfavorable | H76: =IF(OR(ABS(F76)>=0.05, ABS(E76)>=5000000), "Material", "Not Material") -> Material
A77: 46113 | B77: Revenue | C77: =SUM('02_Actual_Revenue'!F602:F641) -> 1832610800 | D77: =SUM('05_Budget'!G602:G641) -> 1.9890404e+09 | E77: =C77-D77 -> -1.5642958e+08 | F77: =IFERROR(E77/D77, 0) -> -0.078645752 | G77: =IF(OR(B77="COGS", B77="Operating Expenses"), IF(E77<=0, "Favorable", "Unfavorable"), IF(E77>=0, "Favorable", "Unfavorable")) -> Unfavorable | H77: =IF(OR(ABS(F77)>=0.05, ABS(E77)>=5000000), "Material", "Not Material") -> Material
A78: 46113 | B78: COGS | C78: =SUM('02_Actual_Revenue'!G602:G641) -> 1.0006827e+09 | D78: =SUM('05_Budget'!H602:H641) -> 1.0838423e+09 | E78: =C78-D78 -> -83159608 | F78: =IFERROR(E78/D78, 0) -> -0.076726667 | G78: =IF(OR(B78="COGS", B78="Operating Expenses"), IF(E78<=0, "Favorable", "Unfavorable"), IF(E78>=0, "Favorable", "Unfavorable")) -> Favorable | H78: =IF(OR(ABS(F78)>=0.05, ABS(E78)>=5000000), "Material", "Not Material") -> Material
A79: 46113 | B79: Gross Profit | C79: =C77-C78 -> 8.319281e+08 | D79: =D77-D78 -> 9.0519806e+08 | E79: =C79-D79 -> -73269967 | F79: =IFERROR(E79/D79, 0) -> -0.080943575 | G79: =IF(OR(B79="COGS", B79="Operating Expenses"), IF(E79<=0, "Favorable", "Unfavorable"), IF(E79>=0, "Favorable", "Unfavorable")) -> Unfavorable | H79: =IF(OR(ABS(F79)>=0.05, ABS(E79)>=5000000), "Material", "Not Material") -> Material
A80: 46113 | B80: Operating Expenses | C80: =SUM('03_Actual_Opex'!E482:E513) -> 396000000 | D80: =SUM('05_Budget'!F1211:F1242) -> 423560000 | E80: =C80-D80 -> -27560000 | F80: =IFERROR(E80/D80, 0) -> -0.065067523 | G80: =IF(OR(B80="COGS", B80="Operating Expenses"), IF(E80<=0, "Favorable", "Unfavorable"), IF(E80>=0, "Favorable", "Unfavorable")) -> Favorable | H80: =IF(OR(ABS(F80)>=0.05, ABS(E80)>=5000000), "Material", "Not Material") -> Material
A81: 46113 | B81: EBIT | C81: =C79-C80 -> 4.359281e+08 | D81: =D79-D80 -> 4.8163806e+08 | E81: =C81-D81 -> -45709967 | F81: =IFERROR(E81/D81, 0) -> -0.094905222 | G81: =IF(OR(B81="COGS", B81="Operating Expenses"), IF(E81<=0, "Favorable", "Unfavorable"), IF(E81>=0, "Favorable", "Unfavorable")) -> Unfavorable | H81: =IF(OR(ABS(F81)>=0.05, ABS(E81)>=5000000), "Material", "Not Material") -> Material
A82: 46143 | B82: Revenue | C82: =SUM('02_Actual_Revenue'!F642:F681) -> 1929064000 | D82: =SUM('05_Budget'!G642:G681) -> 2.0937267e+09 | E82: =C82-D82 -> -1.6466271e+08 | F82: =IFERROR(E82/D82, 0) -> -0.078645752 | G82: =IF(OR(B82="COGS", B82="Operating Expenses"), IF(E82<=0, "Favorable", "Unfavorable"), IF(E82>=0, "Favorable", "Unfavorable")) -> Unfavorable | H82: =IF(OR(ABS(F82)>=0.05, ABS(E82)>=5000000), "Material", "Not Material") -> Material
A83: 46143 | B83: COGS | C83: =SUM('02_Actual_Revenue'!G642:G681) -> 1053350215 | D83: =SUM('05_Budget'!H642:H681) -> 1.1408866e+09 | E83: =C83-D83 -> -87536430 | F83: =IFERROR(E83/D83, 0) -> -0.076726667 | G83: =IF(OR(B83="COGS", B83="Operating Expenses"), IF(E83<=0, "Favorable", "Unfavorable"), IF(E83>=0, "Favorable", "Unfavorable")) -> Favorable | H83: =IF(OR(ABS(F83)>=0.05, ABS(E83)>=5000000), "Material", "Not Material") -> Material
A84: 46143 | B84: Gross Profit | C84: =C82-C83 -> 875713785 | D84: =D82-D83 -> 9.5284007e+08 | E84: =C84-D84 -> -77126281 | F84: =IFERROR(E84/D84, 0) -> -0.080943575 | G84: =IF(OR(B84="COGS", B84="Operating Expenses"), IF(E84<=0, "Favorable", "Unfavorable"), IF(E84>=0, "Favorable", "Unfavorable")) -> Unfavorable | H84: =IF(OR(ABS(F84)>=0.05, ABS(E84)>=5000000), "Material", "Not Material") -> Material
A85: 46143 | B85: Operating Expenses | C85: =SUM('03_Actual_Opex'!E514:E545) -> 396000000 | D85: =SUM('05_Budget'!F1243:F1274) -> 423560000 | E85: =C85-D85 -> -27560000 | F85: =IFERROR(E85/D85, 0) -> -0.065067523 | G85: =IF(OR(B85="COGS", B85="Operating Expenses"), IF(E85<=0, "Favorable", "Unfavorable"), IF(E85>=0, "Favorable", "Unfavorable")) -> Favorable | H85: =IF(OR(ABS(F85)>=0.05, ABS(E85)>=5000000), "Material", "Not Material") -> Material
A86: 46143 | B86: EBIT | C86: =C84-C85 -> 479713785 | D86: =D84-D85 -> 5.2928007e+08 | E86: =C86-D86 -> -49566281 | F86: =IFERROR(E86/D86, 0) -> -0.093648494 | G86: =IF(OR(B86="COGS", B86="Operating Expenses"), IF(E86<=0, "Favorable", "Unfavorable"), IF(E86>=0, "Favorable", "Unfavorable")) -> Unfavorable | H86: =IF(OR(ABS(F86)>=0.05, ABS(E86)>=5000000), "Material", "Not Material") -> Material
A87: 46174 | B87: Revenue | C87: =SUM('02_Actual_Revenue'!F682:F721) -> 1967645280 | D87: =SUM('05_Budget'!G682:G721) -> 2.1356012e+09 | E87: =C87-D87 -> -1.6795597e+08 | F87: =IFERROR(E87/D87, 0) -> -0.078645752 | G87: =IF(OR(B87="COGS", B87="Operating Expenses"), IF(E87<=0, "Favorable", "Unfavorable"), IF(E87>=0, "Favorable", "Unfavorable")) -> Unfavorable | H87: =IF(OR(ABS(F87)>=0.05, ABS(E87)>=5000000), "Material", "Not Material") -> Material
A88: 46174 | B88: COGS | C88: =SUM('02_Actual_Revenue'!G682:G721) -> 1.0744172e+09 | D88: =SUM('05_Budget'!H682:H721) -> 1.1637044e+09 | E88: =C88-D88 -> -89287158 | F88: =IFERROR(E88/D88, 0) -> -0.076726667 | G88: =IF(OR(B88="COGS", B88="Operating Expenses"), IF(E88<=0, "Favorable", "Unfavorable"), IF(E88>=0, "Favorable", "Unfavorable")) -> Favorable | H88: =IF(OR(ABS(F88)>=0.05, ABS(E88)>=5000000), "Material", "Not Material") -> Material
A89: 46174 | B89: Gross Profit | C89: =C87-C88 -> 8.9322806e+08 | D89: =D87-D88 -> 9.7189687e+08 | E89: =C89-D89 -> -78668807 | F89: =IFERROR(E89/D89, 0) -> -0.080943575 | G89: =IF(OR(B89="COGS", B89="Operating Expenses"), IF(E89<=0, "Favorable", "Unfavorable"), IF(E89>=0, "Favorable", "Unfavorable")) -> Unfavorable | H89: =IF(OR(ABS(F89)>=0.05, ABS(E89)>=5000000), "Material", "Not Material") -> Material
A90: 46174 | B90: Operating Expenses | C90: =SUM('03_Actual_Opex'!E546:E577) -> 396000000 | D90: =SUM('05_Budget'!F1275:F1306) -> 423560000 | E90: =C90-D90 -> -27560000 | F90: =IFERROR(E90/D90, 0) -> -0.065067523 | G90: =IF(OR(B90="COGS", B90="Operating Expenses"), IF(E90<=0, "Favorable", "Unfavorable"), IF(E90>=0, "Favorable", "Unfavorable")) -> Favorable | H90: =IF(OR(ABS(F90)>=0.05, ABS(E90)>=5000000), "Material", "Not Material") -> Material
A91: 46174 | B91: EBIT | C91: =C89-C90 -> 4.9722806e+08 | D91: =D89-D90 -> 5.4833687e+08 | E91: =C91-D91 -> -51108807 | F91: =IFERROR(E91/D91, 0) -> -0.09320695 | G91: =IF(OR(B91="COGS", B91="Operating Expenses"), IF(E91<=0, "Favorable", "Unfavorable"), IF(E91>=0, "Favorable", "Unfavorable")) -> Unfavorable | H91: =IF(OR(ABS(F91)>=0.05, ABS(E91)>=5000000), "Material", "Not Material") -> Material

Sheet 09_Scenarios
A1: $M | B1: Downside | C1: Base | D1: Upside
A2: Revenue | B2: =C2*(1-0.03) -> 3.6353377e+10 | C2: ='07_PnL'!B4 -> 3.7477708e+10 | D2: =C2*(1+0.03) -> 3.8602039e+10
A3: Gross Profit | B3: =C3*(1-0.03) -> 1.6544162e+10 | C3: ='07_PnL'!B6 -> 1.7055837e+10 | D3: =C3*(1+0.03) -> 1.7567512e+10
A4: Gross Margin | B4: =B3/B2 -> 0.45509285 | C4: ='07_PnL'!B7 -> 0.45509285 | D4: =D3/D2 -> 0.45509285
A5: EBIT | B5: =C5*(1-0.03) -> 9.1488045e+09 | C5: ='07_PnL'!B9 -> 9.4317572e+09 | D5: =C5*(1+0.03) -> 9.7147099e+09
A6: EBIT Margin | B6: =B5/B2 -> 0.25166313 | C6: ='07_PnL'!B10 -> 0.25166313 | D6: =D5/D2 -> 0.25166313

Sheet 10_Management_Summary
A1: Top KPI Scorecard Table
A3: $M | B3: #
A4: Revenue | B4: ='02_Actual_Revenue'!B723 -> 34530245600
A5: Revenue vs Budget | B5: ='02_Actual_Revenue'!B723-'05_Budget'!B723 -> -2.9474625e+09
A6: Gross Margin | B6: ='02_Actual_Revenue'!B726 -> 0.45395787
A7: EBIT | B7: ='02_Actual_Revenue'!B725-'03_Actual_Opex'!B579 -> 8.5472768e+09
A8: EBIT vs Budget | B8: =B7-'07_PnL'!B9 -> -8.8448043e+08
A9: FY Forecast | B9: ='06_Forecast'!E4 -> 3.7245903e+10
A10: Forecast vs Budget | B10: =B9-'05_Budget'!B723 -> -2.3180541e+08
A11: Headcount | B11: =SUM('04_Actual_Headcount'!C138:C145) -> 4050
A13: Top Risks
A15: High fixed monthly Opex ($396.00M) causing margin compression in Downside scenario
A16: R&D and IT budget growth (9% and 8%) outpacing top-line revenue expansion
A17: Marketing expansion (7% budget, 6% headcount) underperforming on conversion efficiency
A19: Top Opportunities
A21: Operating leverage expansion in Upside scenario ($38.60B Revenue)
A22: Facilities and G&A spend optimization (5% budget, 2%–3% headcount)
A23: Direct COGS reduction to expand Gross Margin beyond 45.51% baseline
A25: Recommended Actions
A27: Implement dynamic Opex guardrails triggered by quarterly revenue hurdles
A28: Tie R&D budget releases (9% growth) to strict product milestone gates
A29: Defer non-critical headcount expansion in HR and Facilities
A30: Re-evaluate supplier agreements to drive direct COGS savings

Sheet 11_Checks
A1: Revenue check
A3: P&L Revenue | B3: ='07_PnL'!B4 -> 3.7477708e+10 | C3: =IF(ABS(SUM('05_Budget'!G2:'05_Budget'!G721) - B3) <= 0.01, "PASS", "FAIL") -> PASS
A5: COGS Check
A7: P&L COGS | B7: ='07_PnL'!B5 -> 2.0421871e+10 | C7: =IF(ABS(SUM('05_Budget'!H2:'05_Budget'!H721) - B7) <= 0.01, "PASS", "FAIL") -> PASS
A9: Gross Profit Check
A11: Gross Profit | B11: ='07_PnL'!B6 -> 1.7055837e+10 | C11: =IF(ABS(('05_Budget'!B723-'05_Budget'!B724) - B11) <= 0.01, "PASS", "FAIL") -> PASS
A13: EBIT Check
A15: EBIT | B15: ='07_PnL'!B9 -> 9.4317572e+09 | C15: =IF(ABS(('05_Budget'!B725-'05_Budget'!B1308) - B15) <= 0.01, "PASS", "FAIL") -> PASS
A17: Forecast Check
A19: Full-Year Forecast | B19: ='06_Forecast'!E4 -> 3.7245903e+10 | C19: =IF(ABS(('06_Forecast'!C4+'06_Forecast'!D4) - B19) <= 0.01, "PASS", "FAIL") -> PASS
A23: Master Check | C23: =IF(COUNTIF(C3:C19, "FAIL") = 0, "MODEL PASS", "MODEL ERROR") -> MODEL PASS
B725: ='11_Checks'!C13 -> 0

Sheet 12_Advance_L&EH
A1: LOOKUP & ERROR HANDLING
A3: Product ID | B3: Region ID | C3: Business Unit | D3: Revenue Model | E3: Lookup Status
A4: P001 | B4: =_xlfn.IFNA(INDEX('02_Actual_Revenue'!$C:$C, MATCH(A4, '02_Actual_Revenue'!$B:$B, 0)), "Not Found") -> R01 | C4: =_xlfn.IFNA(INDEX('02_Actual_Revenue'!$D:$D, MATCH(A4, '02_Actual_Revenue'!$B:$B, 0)), "Not Found") -> 230000 | D4: =_xlfn.IFNA(INDEX('02_Actual_Revenue'!$G:$G, MATCH(A4, '02_Actual_Revenue'!$B:$B, 0)), "Not Found") -> 99677400 | E4: =_xlfn.IFNA(IF(ISNUMBER(MATCH(A4, '02_Actual_Revenue'!$B:$B, 0)), "Valid", "Invalid Product ID"), "Invalid Product ID") -> Valid
A5: P002 | B5: =_xlfn.IFNA(INDEX('02_Actual_Revenue'!$C:$C, MATCH(A5, '02_Actual_Revenue'!$B:$B, 0)), "Not Found") -> R01 | C5: =_xlfn.IFNA(INDEX('02_Actual_Revenue'!$D:$D, MATCH(A5, '02_Actual_Revenue'!$B:$B, 0)), "Not Found") -> 110400 | D5: =_xlfn.IFNA(INDEX('02_Actual_Revenue'!$G:$G, MATCH(A5, '02_Actual_Revenue'!$B:$B, 0)), "Not Found") -> 63967968 | E5: =_xlfn.IFNA(IF(ISNUMBER(MATCH(A5, '02_Actual_Revenue'!$B:$B, 0)), "Valid", "Invalid Product ID"), "Invalid Product ID") -> Valid
A6: P003 | B6: =_xlfn.IFNA(INDEX('02_Actual_Revenue'!$C:$C, MATCH(A6, '02_Actual_Revenue'!$B:$B, 0)), "Not Found") -> R01 | C6: =_xlfn.IFNA(INDEX('02_Actual_Revenue'!$D:$D, MATCH(A6, '02_Actual_Revenue'!$B:$B, 0)), "Not Found") -> 128800 | D6: =_xlfn.IFNA(INDEX('02_Actual_Revenue'!$G:$G, MATCH(A6, '02_Actual_Revenue'!$B:$B, 0)), "Not Found") -> 42426720 | E6: =_xlfn.IFNA(IF(ISNUMBER(MATCH(A6, '02_Actual_Revenue'!$B:$B, 0)), "Valid", "Invalid Product ID"), "Invalid Product ID") -> Valid
A7: P004 | B7: =_xlfn.IFNA(INDEX('02_Actual_Revenue'!$C:$C, MATCH(A7, '02_Actual_Revenue'!$B:$B, 0)), "Not Found") -> R01 | C7: =_xlfn.IFNA(INDEX('02_Actual_Revenue'!$D:$D, MATCH(A7, '02_Actual_Revenue'!$B:$B, 0)), "Not Found") -> 64400 | D7: =_xlfn.IFNA(INDEX('02_Actual_Revenue'!$G:$G, MATCH(A7, '02_Actual_Revenue'!$B:$B, 0)), "Not Found") -> 42468580 | E7: =_xlfn.IFNA(IF(ISNUMBER(MATCH(A7, '02_Actual_Revenue'!$B:$B, 0)), "Valid", "Invalid Product ID"), "Invalid Product ID") -> Valid

Sheet 13_Advance_DAMA
A1: DYNAMIC ARRAY MANAGEMENT ANALYSIS
A3: Unique Business Units | B3: Unique Products | D3: Material Variance Watchlist
A4: {=_xlfn._xlws.SORT(_xlfn.UNIQUE('05_Budget'!D2:D721))} -> 34650 | B4: {=_xlfn._xlws.SORT(_xlfn.UNIQUE('05_Budget'!B2:B721))} -> P001 | D4: {=_xlfn._xlws.SORT(_xlfn._xlws.FILTER('08_Variance'!A2:H91,'08_Variance'!H2:H91="Material","No material variances"),5,-1)} -> 45658 | E4: Operating Expenses | F4: 396000000 | G4: 423560000 | H4: -27560000 | I4: -0.065067523 | J4: Favorable | K4: Material
A5: 35420 | B5: P002 | D5: 45689 | E5: Operating Expenses | F5: 396000000 | G5: 423560000 | H5: -27560000 | I5: -0.065067523 | J5: Favorable | K5: Material
A6: 36575 | B6: P003 | D6: 45717 | E6: Operating Expenses | F6: 396000000 | G6: 423560000 | H6: -27560000 | I6: -0.065067523 | J6: Favorable | K6: Material
A7: 36960 | B7: P004 | D7: 45748 | E7: Operating Expenses | F7: 396000000 | G7: 423560000 | H7: -27560000 | I7: -0.065067523 | J7: Favorable | K7: Material
A8: 38500 | B8: P005 | D8: 45778 | E8: Operating Expenses | F8: 396000000 | G8: 423560000 | H8: -27560000 | I8: -0.065067523 | J8: Favorable | K8: Material
A9: 39270 | B9: P006 | D9: 45809 | E9: Operating Expenses | F9: 396000000 | G9: 423560000 | H9: -27560000 | I9: -0.065067523 | J9: Favorable | K9: Material
A10: 39655 | B10: P007 | D10: 45839 | E10: Operating Expenses | F10: 396000000 | G10: 423560000 | H10: -27560000 | I10: -0.065067523 | J10: Favorable | K10: Material
A11: 40425 | B11: P008 | D11: 45870 | E11: Operating Expenses | F11: 396000000 | G11: 423560000 | H11: -27560000 | I11: -0.065067523 | J11: Favorable | K11: Material
A12: 43120 | B12: P009 | D12: 45901 | E12: Operating Expenses | F12: 396000000 | G12: 423560000 | H12: -27560000 | I12: -0.065067523 | J12: Favorable | K12: Material
A13: 45430 | B13: P010 | D13: 45931 | E13: Operating Expenses | F13: 396000000 | G13: 423560000 | H13: -27560000 | I13: -0.065067523 | J13: Favorable | K13: Material
A14: 53550 | D14: 45962 | E14: Operating Expenses | F14: 396000000 | G14: 423560000 | H14: -27560000 | I14: -0.065067523 | J14: Favorable | K14: Material
A15: 54740 | D15: 45992 | E15: Operating Expenses | F15: 396000000 | G15: 423560000 | H15: -27560000 | I15: -0.065067523 | J15: Favorable | K15: Material
A16: 56525 | D16: 46023 | E16: Operating Expenses | F16: 396000000 | G16: 423560000 | H16: -27560000 | I16: -0.065067523 | J16: Favorable | K16: Material
A17: 57120 | D17: 46054 | E17: Operating Expenses | F17: 396000000 | G17: 423560000 | H17: -27560000 | I17: -0.065067523 | J17: Favorable | K17: Material
A18: 59400 | D18: 46082 | E18: Operating Expenses | F18: 396000000 | G18: 423560000 | H18: -27560000 | I18: -0.065067523 | J18: Favorable | K18: Material
A19: 59500 | D19: 46113 | E19: Operating Expenses | F19: 396000000 | G19: 423560000 | H19: -27560000 | I19: -0.065067523 | J19: Favorable | K19: Material
A20: 59850 | D20: 46143 | E20: Operating Expenses | F20: 396000000 | G20: 423560000 | H20: -27560000 | I20: -0.065067523 | J20: Favorable | K20: Material
A21: 60690 | D21: 46174 | E21: Operating Expenses | F21: 396000000 | G21: 423560000 | H21: -27560000 | I21: -0.065067523 | J21: Favorable | K21: Material
A22: 60720 | D22: 45689 | E22: EBIT | F22: 3.9214241e+08 | G22: 4.3399606e+08 | H22: -41853653 | I22: -0.096437864 | J22: Unfavorable | K22: Material
A23: 61180 | D23: 46054 | E23: EBIT | F23: 3.9214241e+08 | G23: 4.3399606e+08 | H23: -41853653 | I23: -0.096437864 | J23: Unfavorable | K23: Material
A24: 61285 | D24: 45658 | E24: EBIT | F24: 4.0965668e+08 | G24: 4.5305286e+08 | H24: -43396179 | I24: -0.095786127 | J24: Unfavorable | K24: Material
A25: 62475 | D25: 46023 | E25: EBIT | F25: 4.0965668e+08 | G25: 4.5305286e+08 | H25: -43396179 | I25: -0.095786127 | J25: Unfavorable | K25: Material
... A93: 119700 | D93: 45992 | E93: Revenue | F93: 2276295520 | G93: 2.4705975e+09 | H93: -1.94302e+08 | I93: -0.078645752 | J93: Unfavorable | K93: Material
A94: 120000
A95: 120360 | D95: MANAGEMENT COMMENTARY
A96: 121380
A97: 122360 | D97: =E16 & " | " & TEXT(I16, "0.0%") -> Operating Expenses | -6.5%
A98: 122400 | D98: ="Management alert: " & E16 & " is " & TEXT(ABS(I16), "0.0%") & " " & IF(I16 < 0, "below", "above") & " expectation." -> Management alert: Operating Expenses is 6.5% below expectation.
A99: 122570 | D99: =_xlfn.TEXTJOIN(" | ", TRUE, J21:J23) -> Favorable | Unfavorable | Unfavorable
A100: 123600
A101: 123750
A102: 124950
A103: 126000
A104: 126350
A105: 126500
A106: 127680
A107: 128800
A108: 130625
A109: 132000
A110: 133000
A111: 133280
... A383: 1416000

Sheet 14_Advance_PA
A1: PIVOT ANALYSIS
A3: Revenue by Business Unit | D3: Revenue by Region | H3: Revenue by Business Unit | N3: Slicers
A4: Units | B4: Sum of Revenue | D4: RegionID | E4: Sum of Revenue
A5: 34650 | B5: 83090700 | D5: R01 | E5: 10307536000
A6: 35420 | B6: 84937160 | D6: R02 | E6: 8761405600
A7: 36575 | B7: 87706850 | D7: R03 | E7: 9792159200
A8: 36960 | B8: 88630080 | D8: R04 | E8: 5669144800
A9: 38500 | B9: 138484500 | D9: Grand Total | E9: 34530245600
A10: 39270 | B10: 141254190
A11: 39655 | B11: 47546345 | D11: Product Performance
A12: 40425 | B12: 48469575 | D12: ProductID | E12: Sum of Revenue | F12: Sum of Units
A13: 43120 | B13: 51700880 | D13: P001 | E13: 10478883750 | F13: 14991250
A14: 45430 | B14: 54470570 | D14: P002 | E14: 7188604200 | F14: 7195800
A15: 53550 | B15: 128412900 | D15: P003 | E15: 4608909900 | F15: 8395100
A16: 54740 | B16: 131266520 | D16: P004 | E16: 5032862450 | F16: 4197550
A17: 56525 | B17: 135546950 | D17: P005 | E17: 3227316300 | F17: 10793700
A18: 57120 | B18: 136973760 | D18: P006 | E18: 1403181000 | F18: 35979000
A19: 59400 | B19: 118681200 | D19: P007 | E19: 575664000 | F19: 23986000
A20: 59500 | B20: 214021500 | D20: P008 | E20: 863496000 | F20: 71958000
A21: 59850 | B21: 143520300 | D21: P009 | E21: 719580000 | F21: 47972000 | H21: Revenue by Region
A22: 60690 | B22: 218301930 | D22: P010 | E22: 431748000 | F22: 53968500
A23: 60720 | B23: 121318560 | D23: Grand Total | E23: 34530245600 | F23: 279436900
A24: 61180 | B24: 146709640
A25: 61285 | B25: 73480715 | D25: Monthly Revenue Trend
A26: 62475 | B26: 74907525 | D26: MonthStart | E26: Sum of Revenue
A27: 62700 | B27: 125274600 | D27: 45658 | E27: 1774738880
A28: 63000 | B28: 151074000 | D28: 45689 | E28: 1736157600
A29: 63175 | B29: 151493650 | D29: 45717 | E29: 1851901440
A30: 63360 | B30: 126593280 | D30: 45748 | E30: 1832610800
A31: 63840 | B31: 153088320 | D31: 45778 | E31: 1929064000
A32: 64400 | B32: 154431200 | D32: 45809 | E32: 1967645280
A33: 66000 | B33: 197802000 | D33: 45839 | E33: 1986935920
A34: 66500 | B34: 398667500 | D34: 45870 | E34: 1967645280
A35: 66640 | B35: 79901360 | D35: 45901 | E35: 1929064000
A36: 67200 | B36: 161145600 | D36: 45931 | E36: 2025517200
A37: 67320 | B37: 201758040 | D37: 45962 | E37: 2160551680
A38: 67830 | B38: 243984510 | D38: 45992 | E38: 2276295520 | H38: Product Performance
A39: 67980 | B39: 67912020 | D39: 46023 | E39: 1774738880
A40: 68495 | B40: 82125505 | D40: 46054 | E40: 1736157600
A41: 69300 | B41: 145322100 | D41: 46082 | E41: 1851901440
A42: 69825 | B42: 83720175 | D42: 46113 | E42: 1832610800
A43: 70000 | B43: 251790000 | D43: 46143 | E43: 1929064000
A44: 70210 | B44: 84181790 | D44: 46174 | E44: 1967645280
A45: 70840 | B45: 77782320 | D45: Grand Total | E45: 34530245600
A46: 71400 | B46: 256825800
A47: 72100 | B47: 86447900
A48: 73150 | B48: 80318700
A49: 73500 | B49: 88126500
A50: 73920 | B50: 155010240
A51: 74480 | B51: 89301520
A52: 77000 | B52: 126819000
A53: 77880 | B53: 77802120
A54: 78400 | B54: 94001600
A55: 78470 | B55: 94085530 | H55: Monthly Revenue Trend
A56: 78540 | B56: 129355380
A57: 79310 | B57: 43541190
A58: 80850 | B58: 44386650
A59: 82600 | B59: 99037400
A60: 86240 | B60: 47345760
A61: 89100 | B61: 53281800
A62: 90860 | B62: 49882140
A63: 91080 | B63: 54465840
A64: 91800 | B64: 183416400
A65: 93840 | B65: 187492320
A66: 94050 | B66: 56241900
A67: 95040 | B67: 56833920
... A384: 1416000 | B384: 16992000
A385: Grand Total | B385: 34530245600

Sheet 15_Advance_S&WA
A1: SCENARIO & WHAT-IF ANALYSIS
A3: Scenario | B3: Downside | C3: Revenue Adjustment | D3: Opex Adjustment
A4: Downside | C4: -0.03 | D4: 0.03
A5: Base | C5: 0 | D5: 0
A6: Upside | C6: 0.03 | D6: -0.02
A8: Selected Revenue Adjustment | C8: =_xlfn.IFNA(INDEX(C4:C6, MATCH(B3, A4:A6, 0)), 0) -> -0.03
A9: Selected Opex Adjustment | C9: =_xlfn.IFNA(INDEX(D4:D6, MATCH(B3, A4:A6, 0)), 0) -> 0.03
A11: Metric | B11: Value
A12: Revenue Growth Input | B12: 0.049542168
A13: Target EBIT Margin | B13: 0.25
A14: Scenario Revenue | B14: ='05_Budget'!B723 * (1 + B12 + C8) -> 3.8210104e+10
A15: Scenario Gross Profit | B15: =B14*'05_Budget'!B726 -> 1.7389145e+10
A16: Scenario EBIT | B16: =B15-('05_Budget'!B1308*(1 + C9)) -> 9.5363428e+09
A17: Scenario EBIT Margin | B17: =B16 / B14 -> 0.24957647

Sheet 16_Advance_MC&EF
A1: MODEL CONTROL & EXCEPTION FLAGS
A3: Control | B3: Result
A4: Product Mapping | B4: PASS
A5: Variance Data | B5: PASS
A6: Scenario Selection | B6: PASS
A7: Revenue Reconciliation | B7: PASS
A8: Gross Profit Reconciliation | B8: PASS
